[
  {
    "time": 1764042300,
    "open": 25997.5996,
    "high": 25997.5996,
    "low": 25924.5508,
    "close": 25965.0,
    "bb_mid": NaN,
    "bb_upper": NaN,
    "bb_lower": NaN,
    "rsi": NaN,
    "ao": NaN
  },
  {
    "time": 1764042600,
    "open": 25963.75,
    "high": 25968.75,
    "low": 25942.5508,
    "close": 25955.8496,
    "bb_mid": NaN,
    "bb_upper": NaN,
    "bb_lower": NaN,
    "rsi": NaN,
    "ao": NaN
  },
  {
    "time": 1764042900,
    "open": 25955.0996,
    "high": 25969.1504,
    "low": 25946.4492,
    "close": 25955.1992,
    "bb_mid": NaN,
    "bb_upper": NaN,
    "bb_lower": NaN,
    "rsi": NaN,
    "ao": NaN
  },
  {
    "time": 1764043200,
    "open": 25954.8496,
    "high": 25979.5996,
    "low": 25953.8008,
    "close": 25977.5508,
    "bb_mid": NaN,
    "bb_upper": NaN,
    "bb_lower": NaN,
    "rsi": NaN,
    "ao": NaN
  },
  {
    "time": 1764043500,
    "open": 25979.4004,
    "high": 25980.6504,
    "low": 25960.9492,
    "close": 25969.5,
    "bb_mid": NaN,
    "bb_upper": NaN,
    "bb_lower": NaN,
    "rsi": NaN,
    "ao": NaN
  },
  {
    "time": 1764043800,
    "open": 25969.4004,
    "high": 25978.6992,
    "low": 25968.25,
    "close": 25969.0996,
    "bb_mid": NaN,
    "bb_upper": NaN,
    "bb_lower": NaN,
    "rsi": NaN,
    "ao": NaN
  },
  {
    "time": 1764044100,
    "open": 25969.0,
    "high": 25975.8008,
    "low": 25961.0508,
    "close": 25961.1504,
    "bb_mid": NaN,
    "bb_upper": NaN,
    "bb_lower": NaN,
    "rsi": NaN,
    "ao": NaN
  },
  {
    "time": 1764044400,
    "open": 25960.25,
    "high": 25988.0996,
    "low": 25952.0996,
    "close": 25983.9004,
    "bb_mid": NaN,
    "bb_upper": NaN,
    "bb_lower": NaN,
    "rsi": NaN,
    "ao": NaN
  },
  {
    "time": 1764044700,
    "open": 25984.0508,
    "high": 25990.5996,
    "low": 25978.9492,
    "close": 25988.4004,
    "bb_mid": NaN,
    "bb_upper": NaN,
    "bb_lower": NaN,
    "rsi": NaN,
    "ao": NaN
  },
  {
    "time": 1764045000,
    "open": 25987.6504,
    "high": 26000.0996,
    "low": 25985.5508,
    "close": 25989.9004,
    "bb_mid": NaN,
    "bb_upper": NaN,
    "bb_lower": NaN,
    "rsi": NaN,
    "ao": NaN
  },
  {
    "time": 1764045300,
    "open": 25988.6504,
    "high": 26005.8496,
    "low": 25988.6504,
    "close": 26005.1504,
    "bb_mid": NaN,
    "bb_upper": NaN,
    "bb_lower": NaN,
    "rsi": NaN,
    "ao": NaN
  },
  {
    "time": 1764045600,
    "open": 26005.6504,
    "high": 26025.25,
    "low": 26004.1504,
    "close": 26018.5996,
    "bb_mid": NaN,
    "bb_upper": NaN,
    "bb_lower": NaN,
    "rsi": NaN,
    "ao": NaN
  },
  {
    "time": 1764045900,
    "open": 26019.3496,
    "high": 26024.0,
    "low": 26013.0,
    "close": 26014.0996,
    "bb_mid": NaN,
    "bb_upper": NaN,
    "bb_lower": NaN,
    "rsi": NaN,
    "ao": NaN
  },
  {
    "time": 1764046200,
    "open": 26013.1992,
    "high": 26019.9492,
    "low": 26005.5,
    "close": 26015.1992,
    "bb_mid": NaN,
    "bb_upper": NaN,
    "bb_lower": NaN,
    "rsi": NaN,
    "ao": NaN
  },
  {
    "time": 1764046500,
    "open": 26014.9492,
    "high": 26020.25,
    "low": 26005.0996,
    "close": 26010.5508,
    "bb_mid": NaN,
    "bb_upper": NaN,
    "bb_lower": NaN,
    "rsi": 43.2954,
    "ao": NaN
  },
  {
    "time": 1764046800,
    "open": 26010.8496,
    "high": 26020.4004,
    "low": 26001.1504,
    "close": 26001.6992,
    "bb_mid": NaN,
    "bb_upper": NaN,
    "bb_lower": NaN,
    "rsi": 40.0233,
    "ao": NaN
  },
  {
    "time": 1764047100,
    "open": 26001.9004,
    "high": 26012.6504,
    "low": 25992.4492,
    "close": 26008.6504,
    "bb_mid": NaN,
    "bb_upper": NaN,
    "bb_lower": NaN,
    "rsi": 43.6265,
    "ao": NaN
  },
  {
    "time": 1764047400,
    "open": 26007.9004,
    "high": 26009.75,
    "low": 25991.4004,
    "close": 25991.4004,
    "bb_mid": NaN,
    "bb_upper": NaN,
    "bb_lower": NaN,
    "rsi": 37.5911,
    "ao": NaN
  },
  {
    "time": 1764047700,
    "open": 25991.75,
    "high": 25991.9004,
    "low": 25982.3496,
    "close": 25984.5,
    "bb_mid": NaN,
    "bb_upper": NaN,
    "bb_lower": NaN,
    "rsi": 35.4768,
    "ao": NaN
  },
  {
    "time": 1764048000,
    "open": 25984.6992,
    "high": 25990.5508,
    "low": 25973.0508,
    "close": 25975.25,
    "bb_mid": 25987.0325,
    "bb_upper": 26028.4049,
    "bb_lower": 25945.6602,
    "rsi": 32.8126,
    "ao": NaN
  },
  {
    "time": 1764048300,
    "open": 25975.4492,
    "high": 25976.0508,
    "low": 25938.4492,
    "close": 25939.0996,
    "bb_mid": 25985.7375,
    "bb_upper": 26031.4115,
    "bb_lower": 25940.0635,
    "rsi": 24.9322,
    "ao": NaN
  },
  {
    "time": 1764048600,
    "open": 25938.9492,
    "high": 25939.9004,
    "low": 25927.1504,
    "close": 25934.9004,
    "bb_mid": 25984.69,
    "bb_upper": 26034.0613,
    "bb_lower": 25935.3188,
    "rsi": 24.205,
    "ao": NaN
  },
  {
    "time": 1764048900,
    "open": 25934.9004,
    "high": 25938.8496,
    "low": 25931.0508,
    "close": 25937.0,
    "bb_mid": 25983.7801,
    "bb_upper": 26036.027,
    "bb_lower": 25931.5331,
    "rsi": 25.377,
    "ao": NaN
  },
  {
    "time": 1764049200,
    "open": 25936.8496,
    "high": 25945.3496,
    "low": 25933.0996,
    "close": 25945.1992,
    "bb_mid": 25982.1625,
    "bb_upper": 26037.1527,
    "bb_lower": 25927.1723,
    "rsi": 29.9332,
    "ao": NaN
  },
  {
    "time": 1764049500,
    "open": 25945.25,
    "high": 25953.8008,
    "low": 25944.4492,
    "close": 25948.8008,
    "bb_mid": 25981.1275,
    "bb_upper": 26037.8723,
    "bb_lower": 25924.3827,
    "rsi": 31.9002,
    "ao": NaN
  },
  {
    "time": 1764049800,
    "open": 25949.0,
    "high": 25953.1992,
    "low": 25942.3496,
    "close": 25950.25,
    "bb_mid": 25980.1851,
    "bb_upper": 26038.3787,
    "bb_lower": 25921.9914,
    "rsi": 32.7186,
    "ao": NaN
  },
  {
    "time": 1764050100,
    "open": 25950.25,
    "high": 25964.8008,
    "low": 25949.5508,
    "close": 25962.8008,
    "bb_mid": 25980.2676,
    "bb_upper": 26038.3521,
    "bb_lower": 25922.183,
    "rsi": 39.5001,
    "ao": NaN
  },
  {
    "time": 1764050400,
    "open": 25962.6992,
    "high": 25966.3496,
    "low": 25958.0996,
    "close": 25965.1992,
    "bb_mid": 25979.3325,
    "bb_upper": 26037.7718,
    "bb_lower": 25920.8932,
    "rsi": 40.7296,
    "ao": NaN
  },
  {
    "time": 1764050700,
    "open": 25965.25,
    "high": 25968.6504,
    "low": 25962.0,
    "close": 25966.9004,
    "bb_mid": 25978.2575,
    "bb_upper": 26036.7854,
    "bb_lower": 25919.7296,
    "rsi": 41.6355,
    "ao": NaN
  },
  {
    "time": 1764051000,
    "open": 25966.5,
    "high": 25969.8008,
    "low": 25950.5508,
    "close": 25952.1504,
    "bb_mid": 25976.37,
    "bb_upper": 26035.7457,
    "bb_lower": 25916.9944,
    "rsi": 36.4353,
    "ao": NaN
  },
  {
    "time": 1764051300,
    "open": 25952.0,
    "high": 25964.4492,
    "low": 25950.6504,
    "close": 25962.6992,
    "bb_mid": 25974.2475,
    "bb_upper": 26032.3118,
    "bb_lower": 25916.1831,
    "rsi": 42.0134,
    "ao": NaN
  },
  {
    "time": 1764051600,
    "open": 25963.5508,
    "high": 25976.3496,
    "low": 25962.3496,
    "close": 25973.6504,
    "bb_mid": 25972.0,
    "bb_upper": 26026.1862,
    "bb_lower": 25917.8138,
    "rsi": 47.1941,
    "ao": NaN
  },
  {
    "time": 1764051900,
    "open": 25973.0,
    "high": 25994.75,
    "low": 25972.25,
    "close": 25987.4492,
    "bb_mid": 25970.6675,
    "bb_upper": 26021.7143,
    "bb_lower": 25919.6206,
    "rsi": 52.9038,
    "ao": NaN
  },
  {
    "time": 1764052200,
    "open": 25987.5,
    "high": 25990.6992,
    "low": 25974.9004,
    "close": 25975.75,
    "bb_mid": 25968.695,
    "bb_upper": 26015.3571,
    "bb_lower": 25922.0329,
    "rsi": 48.1501,
    "ao": -4.0383
  },
  {
    "time": 1764052500,
    "open": 25976.3496,
    "high": 25991.1504,
    "low": 25975.8496,
    "close": 25988.5996,
    "bb_mid": 25967.5975,
    "bb_upper": 26011.0355,
    "bb_lower": 25924.1594,
    "rsi": 53.1314,
    "ao": -0.033
  },
  {
    "time": 1764052800,
    "open": 25988.3008,
    "high": 25988.75,
    "low": 25973.4492,
    "close": 25981.4004,
    "bb_mid": 25966.5825,
    "bb_upper": 26007.5436,
    "bb_lower": 25925.6214,
    "rsi": 50.2203,
    "ao": 3.9285
  },
  {
    "time": 1764053100,
    "open": 25981.5996,
    "high": 25986.0,
    "low": 25963.0,
    "close": 25964.4492,
    "bb_mid": 25964.3725,
    "bb_upper": 26000.2282,
    "bb_lower": 25928.5167,
    "rsi": 44.0942,
    "ao": 4.4674
  },
  {
    "time": 1764053400,
    "open": 25964.0,
    "high": 25964.75,
    "low": 25954.3496,
    "close": 25957.9492,
    "bb_mid": 25962.6999,
    "bb_upper": 25996.2967,
    "bb_lower": 25929.1031,
    "rsi": 41.9796,
    "ao": -0.1124
  },
  {
    "time": 1764053700,
    "open": 25958.3496,
    "high": 25975.9004,
    "low": 25954.5508,
    "close": 25957.9492,
    "bb_mid": 25961.3724,
    "bb_upper": 25993.404,
    "bb_lower": 25929.3407,
    "rsi": 41.9796,
    "ao": -3.4633
  },
  {
    "time": 1764054000,
    "open": 25958.1992,
    "high": 25969.6504,
    "low": 25958.1992,
    "close": 25966.9004,
    "bb_mid": 25960.9549,
    "bb_upper": 25992.4379,
    "bb_lower": 25929.4718,
    "rsi": 46.1074,
    "ao": -7.0974
  },
  {
    "time": 1764054300,
    "open": 25966.6992,
    "high": 25977.8008,
    "low": 25964.75,
    "close": 25974.75,
    "bb_mid": 25962.7374,
    "bb_upper": 25993.0245,
    "bb_lower": 25932.4503,
    "rsi": 49.5004,
    "ao": -9.1461
  },
  {
    "time": 1764054600,
    "open": 25974.6504,
    "high": 25990.1504,
    "low": 25972.9004,
    "close": 25987.4492,
    "bb_mid": 25965.3648,
    "bb_upper": 25994.5824,
    "bb_lower": 25936.1472,
    "rsi": 54.4922,
    "ao": -8.077
  },
  {
    "time": 1764054900,
    "open": 25987.25,
    "high": 25994.1992,
    "low": 25986.3008,
    "close": 25986.3008,
    "bb_mid": 25967.8299,
    "bb_upper": 25995.2339,
    "bb_lower": 25940.4259,
    "rsi": 53.9726,
    "ao": -2.0981
  },
  {
    "time": 1764055200,
    "open": 25986.3008,
    "high": 25998.8008,
    "low": 25979.25,
    "close": 25994.5,
    "bb_mid": 25970.2949,
    "bb_upper": 25997.9954,
    "bb_lower": 25942.5944,
    "rsi": 57.1164,
    "ao": 2.7737
  },
  {
    "time": 1764055500,
    "open": 25994.5508,
    "high": 26002.1992,
    "low": 25983.9004,
    "close": 25983.9004,
    "bb_mid": 25972.0499,
    "bb_upper": 25998.4328,
    "bb_lower": 25945.667,
    "rsi": 52.1567,
    "ao": 8.7222
  },
  {
    "time": 1764055800,
    "open": 25984.0508,
    "high": 25984.1992,
    "low": 25969.6504,
    "close": 25974.9492,
    "bb_mid": 25973.2849,
    "bb_upper": 25997.6027,
    "bb_lower": 25948.967,
    "rsi": 48.3393,
    "ao": 10.9631
  },
  {
    "time": 1764056100,
    "open": 25974.8008,
    "high": 26006.4004,
    "low": 25973.5996,
    "close": 26001.5508,
    "bb_mid": 25975.2224,
    "bb_upper": 26002.0666,
    "bb_lower": 25948.3781,
    "rsi": 58.1439,
    "ao": 13.4963
  },
  {
    "time": 1764056400,
    "open": 26002.3496,
    "high": 26009.3008,
    "low": 25986.1504,
    "close": 25990.25,
    "bb_mid": 25976.4749,
    "bb_upper": 26003.6852,
    "bb_lower": 25949.2646,
    "rsi": 53.4988,
    "ao": 15.4325
  },
  {
    "time": 1764056700,
    "open": 25990.0,
    "high": 26001.6992,
    "low": 25987.6504,
    "close": 25990.5996,
    "bb_mid": 25977.6599,
    "bb_upper": 26005.177,
    "bb_lower": 25950.1428,
    "rsi": 53.6222,
    "ao": 17.0918
  },
  {
    "time": 1764057000,
    "open": 25991.3008,
    "high": 26002.0,
    "low": 25983.3496,
    "close": 26000.3008,
    "bb_mid": 25980.0674,
    "bb_upper": 26006.5949,
    "bb_lower": 25953.5399,
    "rsi": 57.0309,
    "ao": 17.5492
  },
  {
    "time": 1764057300,
    "open": 26000.0996,
    "high": 26014.8496,
    "low": 25998.1992,
    "close": 26009.1992,
    "bb_mid": 25982.3924,
    "bb_upper": 26010.6078,
    "bb_lower": 25954.177,
    "rsi": 59.9393,
    "ao": 23.3522
  },
  {
    "time": 1764057600,
    "open": 26008.5996,
    "high": 26012.5996,
    "low": 25989.1992,
    "close": 26004.9492,
    "bb_mid": 25983.9573,
    "bb_upper": 26013.5685,
    "bb_lower": 25954.3461,
    "rsi": 57.9228,
    "ao": 25.5226
  },
  {
    "time": 1764057900,
    "open": 26003.9492,
    "high": 26013.4004,
    "low": 26000.4004,
    "close": 26011.3496,
    "bb_mid": 25985.1523,
    "bb_upper": 26017.1869,
    "bb_lower": 25953.1178,
    "rsi": 60.0999,
    "ao": 26.7759
  },
  {
    "time": 1764058200,
    "open": 26010.75,
    "high": 26012.3496,
    "low": 25992.8008,
    "close": 25996.4492,
    "bb_mid": 25986.1873,
    "bb_upper": 26018.2802,
    "bb_lower": 25954.0944,
    "rsi": 53.1989,
    "ao": 27.745
  },
  {
    "time": 1764058500,
    "open": 25995.6992,
    "high": 26009.25,
    "low": 25987.1992,
    "close": 25999.0996,
    "bb_mid": 25986.7123,
    "bb_upper": 26019.3109,
    "bb_lower": 25954.1137,
    "rsi": 54.2061,
    "ao": 27.6498
  },
  {
    "time": 1764058800,
    "open": 25998.5996,
    "high": 26008.75,
    "low": 25996.1992,
    "close": 26007.5508,
    "bb_mid": 25988.0198,
    "bb_upper": 26021.7978,
    "bb_lower": 25954.2418,
    "rsi": 57.3576,
    "ao": 24.8119
  },
  {
    "time": 1764059100,
    "open": 26008.0996,
    "high": 26010.5,
    "low": 26001.1992,
    "close": 26008.3496,
    "bb_mid": 25990.2148,
    "bb_upper": 26023.2408,
    "bb_lower": 25957.1889,
    "rsi": 57.6543,
    "ao": 23.7167
  },
  {
    "time": 1764059400,
    "open": 26008.3496,
    "high": 26023.4492,
    "low": 26006.4492,
    "close": 26019.75,
    "bb_mid": 25993.3049,
    "bb_upper": 26025.1637,
    "bb_lower": 25961.4461,
    "rsi": 61.7445,
    "ao": 23.0993
  },
  {
    "time": 1764059700,
    "open": 26020.1992,
    "high": 26028.5508,
    "low": 26013.5996,
    "close": 26013.5996,
    "bb_mid": 25996.0874,
    "bb_upper": 26024.4763,
    "bb_lower": 25967.6985,
    "rsi": 58.4636,
    "ao": 24.6831
  },
  {
    "time": 1764060000,
    "open": 26014.1504,
    "high": 26023.8496,
    "low": 26012.9004,
    "close": 26020.25,
    "bb_mid": 25998.7549,
    "bb_upper": 26025.5791,
    "bb_lower": 25971.9306,
    "rsi": 60.884,
    "ao": 26.6367
  },
  {
    "time": 1764060300,
    "open": 26020.5996,
    "high": 26032.0996,
    "low": 26003.0508,
    "close": 26004.1992,
    "bb_mid": 26000.2273,
    "bb_upper": 26024.6269,
    "bb_lower": 25975.8278,
    "rsi": 52.8757,
    "ao": 27.8803
  },
  {
    "time": 1764060600,
    "open": 26003.6504,
    "high": 26012.9004,
    "low": 25989.0,
    "close": 25990.9004,
    "bb_mid": 26000.3999,
    "bb_upper": 26024.4655,
    "bb_lower": 25976.3343,
    "rsi": 47.3218,
    "ao": 25.7615
  },
  {
    "time": 1764060900,
    "open": 25989.6504,
    "high": 25992.1504,
    "low": 25972.0996,
    "close": 25973.6504,
    "bb_mid": 25999.7674,
    "bb_upper": 26025.9639,
    "bb_lower": 25973.5708,
    "rsi": 41.2669,
    "ao": 18.7025
  },
  {
    "time": 1764061200,
    "open": 25972.5508,
    "high": 25972.75,
    "low": 25953.75,
    "close": 25958.4492,
    "bb_mid": 25997.9648,
    "bb_upper": 26029.9983,
    "bb_lower": 25965.9313,
    "rsi": 36.7986,
    "ao": 7.047
  },
  {
    "time": 1764061500,
    "open": 25958.4492,
    "high": 25968.9004,
    "low": 25943.75,
    "close": 25947.3496,
    "bb_mid": 25996.1373,
    "bb_upper": 26034.9933,
    "bb_lower": 25957.2813,
    "rsi": 33.9112,
    "ao": -5.3269
  },
  {
    "time": 1764061800,
    "open": 25946.6992,
    "high": 25966.5,
    "low": 25942.9004,
    "close": 25963.4004,
    "bb_mid": 25995.5599,
    "bb_upper": 26036.0505,
    "bb_lower": 25955.0692,
    "rsi": 41.1075,
    "ao": -17.471
  },
  {
    "time": 1764062100,
    "open": 25962.75,
    "high": 25966.8496,
    "low": 25950.6992,
    "close": 25959.0996,
    "bb_mid": 25993.4373,
    "bb_upper": 26036.944,
    "bb_lower": 25949.9306,
    "rsi": 39.8552,
    "ao": -25.179
  },
  {
    "time": 1764062400,
    "open": 25959.25,
    "high": 25963.5996,
    "low": 25920.3496,
    "close": 25921.6992,
    "bb_mid": 25990.0098,
    "bb_upper": 26044.09,
    "bb_lower": 25935.9296,
    "rsi": 31.0086,
    "ao": -32.0083
  },
  {
    "time": 1764062700,
    "open": 25921.1504,
    "high": 25932.5996,
    "low": 25898.75,
    "close": 25899.8008,
    "bb_mid": 25985.4698,
    "bb_upper": 26052.9309,
    "bb_lower": 25918.0087,
    "rsi": 27.2015,
    "ao": -39.5285
  },
  {
    "time": 1764063000,
    "open": 25899.3008,
    "high": 25920.4004,
    "low": 25869.75,
    "close": 25883.4004,
    "bb_mid": 25979.6248,
    "bb_upper": 26060.5825,
    "bb_lower": 25898.6671,
    "rsi": 24.7505,
    "ao": -49.2484
  },
  {
    "time": 1764063300,
    "open": 25884.8496,
    "high": 25901.1992,
    "low": 25879.8008,
    "close": 25887.4004,
    "bb_mid": 25973.5349,
    "bb_upper": 26063.0025,
    "bb_lower": 25884.0673,
    "rsi": 26.4902,
    "ao": -59.6178
  },
  {
    "time": 1764063600,
    "open": 25885.4492,
    "high": 25901.8496,
    "low": 25881.6504,
    "close": 25886.0,
    "bb_mid": 25967.5874,
    "bb_upper": 26063.8209,
    "bb_lower": 25871.3539,
    "rsi": 26.2613,
    "ao": -71.0286
  },
  {
    "time": 1764063900,
    "open": 25886.0508,
    "high": 25886.0508,
    "low": 25877.0,
    "close": 25879.3496,
    "bb_mid": 25960.9874,
    "bb_upper": 26062.5424,
    "bb_lower": 25859.4324,
    "rsi": 25.1499,
    "ao": -80.6566
  },
  {
    "time": 1764064200,
    "open": 25880.0,
    "high": 25882.5996,
    "low": 25870.0996,
    "close": 25873.5,
    "bb_mid": 25954.8399,
    "bb_upper": 26062.0824,
    "bb_lower": 25847.5975,
    "rsi": 24.1804,
    "ao": -85.9459
  },
  {
    "time": 1764064500,
    "open": 25872.75,
    "high": 25874.25,
    "low": 25858.4004,
    "close": 25860.3008,
    "bb_mid": 25947.9,
    "bb_upper": 26060.8927,
    "bb_lower": 25834.9073,
    "rsi": 22.1096,
    "ao": -88.6092
  },
  {
    "time": 1764128700,
    "open": 25842.9492,
    "high": 25969.0508,
    "low": 25842.9492,
    "close": 25969.0508,
    "bb_mid": 25945.975,
    "bb_upper": 26055.9606,
    "bb_lower": 25835.9894,
    "rsi": 55.7416,
    "ao": -83.2878
  },
  {
    "time": 1764129000,
    "open": 25969.6504,
    "high": 25977.3496,
    "low": 25965.0996,
    "close": 25969.3496,
    "bb_mid": 25944.025,
    "bb_upper": 26050.687,
    "bb_lower": 25837.363,
    "rsi": 55.7981,
    "ao": -66.8333
  },
  {
    "time": 1764129300,
    "open": 25969.3008,
    "high": 25983.4004,
    "low": 25965.5996,
    "close": 25979.3008,
    "bb_mid": 25942.0025,
    "bb_upper": 26044.0531,
    "bb_lower": 25839.952,
    "rsi": 57.7325,
    "ao": -47.8112
  },
  {
    "time": 1764129600,
    "open": 25979.9004,
    "high": 26014.5508,
    "low": 25979.5996,
    "close": 26011.0,
    "bb_mid": 25941.8726,
    "bb_upper": 26043.545,
    "bb_lower": 25840.2001,
    "rsi": 63.2496,
    "ao": -23.7845
  },
  {
    "time": 1764129900,
    "open": 26011.4492,
    "high": 26015.75,
    "low": 25999.0996,
    "close": 26003.0996,
    "bb_mid": 25941.015,
    "bb_upper": 26040.1621,
    "bb_lower": 25841.868,
    "rsi": 61.1087,
    "ao": 3.5384
  },
  {
    "time": 1764130200,
    "open": 26003.3008,
    "high": 26025.4492,
    "low": 26000.8008,
    "close": 26024.5996,
    "bb_mid": 25942.0351,
    "bb_upper": 26044.2902,
    "bb_lower": 25839.78,
    "rsi": 64.6186,
    "ao": 24.2832
  },
  {
    "time": 1764130500,
    "open": 26024.0996,
    "high": 26049.6504,
    "low": 26024.0996,
    "close": 26049.4492,
    "bb_mid": 25944.9625,
    "bb_upper": 26056.0766,
    "bb_lower": 25833.8484,
    "rsi": 68.1917,
    "ao": 36.2619
  },
  {
    "time": 1764130800,
    "open": 26049.1992,
    "high": 26080.0508,
    "low": 26048.3008,
    "close": 26077.3496,
    "bb_mid": 25950.1475,
    "bb_upper": 26075.645,
    "bb_lower": 25824.6499,
    "rsi": 71.653,
    "ao": 52.1529
  },
  {
    "time": 1764131100,
    "open": 26076.3008,
    "high": 26084.1504,
    "low": 26068.0508,
    "close": 26077.9492,
    "bb_mid": 25956.1225,
    "bb_upper": 26094.0478,
    "bb_lower": 25818.1971,
    "rsi": 71.7243,
    "ao": 65.5042
  },
  {
    "time": 1764131400,
    "open": 26077.4492,
    "high": 26092.4492,
    "low": 26077.4492,
    "close": 26087.4004,
    "bb_mid": 25963.125,
    "bb_upper": 26112.8879,
    "bb_lower": 25813.3621,
    "rsi": 72.8807,
    "ao": 78.7025
  },
  {
    "time": 1764131700,
    "open": 26087.25,
    "high": 26098.1992,
    "low": 26085.9004,
    "close": 26092.8008,
    "bb_mid": 25969.595,
    "bb_upper": 26130.1964,
    "bb_lower": 25808.9936,
    "rsi": 73.5465,
    "ao": 91.8066
  },
  {
    "time": 1764132000,
    "open": 26092.9492,
    "high": 26095.1992,
    "low": 26074.75,
    "close": 26084.5,
    "bb_mid": 25975.865,
    "bb_upper": 26144.3397,
    "bb_lower": 25807.3904,
    "rsi": 70.6744,
    "ao": 99.1302
  },
  {
    "time": 1764132300,
    "open": 26084.25,
    "high": 26092.6992,
    "low": 26082.0508,
    "close": 26084.3496,
    "bb_mid": 25983.9976,
    "bb_upper": 26157.1022,
    "bb_lower": 25810.8929,
    "rsi": 70.6206,
    "ao": 101.2759
  },
  {
    "time": 1764132600,
    "open": 26085.5996,
    "high": 26085.5996,
    "low": 26068.1504,
    "close": 26077.0996,
    "bb_mid": 25992.8625,
    "bb_upper": 26165.9715,
    "bb_lower": 25819.7535,
    "rsi": 67.9354,
    "ao": 99.1176
  },
  {
    "time": 1764132900,
    "open": 26077.4004,
    "high": 26079.6504,
    "low": 26061.9004,
    "close": 26067.25,
    "bb_mid": 26002.055,
    "bb_upper": 26170.1423,
    "bb_lower": 25833.9676,
    "rsi": 64.3552,
    "ao": 94.274
  },
  {
    "time": 1764133200,
    "open": 26067.3008,
    "high": 26088.4492,
    "low": 26066.1992,
    "close": 26078.8008,
    "bb_mid": 26011.625,
    "bb_upper": 26173.9217,
    "bb_lower": 25849.3283,
    "rsi": 66.5795,
    "ao": 89.2266
  },
  {
    "time": 1764133500,
    "open": 26077.9492,
    "high": 26089.1992,
    "low": 26073.0,
    "close": 26088.4004,
    "bb_mid": 26021.745,
    "bb_upper": 26176.1065,
    "bb_lower": 25867.3835,
    "rsi": 68.3473,
    "ao": 86.506
  },
  {
    "time": 1764133800,
    "open": 26088.5,
    "high": 26093.4004,
    "low": 26084.5508,
    "close": 26092.1992,
    "bb_mid": 26032.3875,
    "bb_upper": 26174.2567,
    "bb_lower": 25890.5183,
    "rsi": 69.0452,
    "ao": 84.8291
  },
  {
    "time": 1764134100,
    "open": 26091.6504,
    "high": 26130.5,
    "low": 26091.6504,
    "close": 26123.4492,
    "bb_mid": 26044.885,
    "bb_upper": 26170.9809,
    "bb_lower": 25918.789,
    "rsi": 74.1029,
    "ao": 88.9427
  },
  {
    "time": 1764134400,
    "open": 26122.9492,
    "high": 26126.0996,
    "low": 26103.5508,
    "close": 26106.5508,
    "bb_mid": 26057.1975,
    "bb_upper": 26151.4818,
    "bb_lower": 25962.9131,
    "rsi": 67.6646,
    "ao": 94.8923
  },
  {
    "time": 1764134700,
    "open": 26106.5508,
    "high": 26114.8008,
    "low": 26103.9492,
    "close": 26109.1504,
    "bb_mid": 26064.2024,
    "bb_upper": 26151.4687,
    "bb_lower": 25976.9362,
    "rsi": 68.1234,
    "ao": 98.1135
  },
  {
    "time": 1764135000,
    "open": 26108.5,
    "high": 26121.9004,
    "low": 26108.5,
    "close": 26118.5,
    "bb_mid": 26071.66,
    "bb_upper": 26149.8124,
    "bb_lower": 25993.5076,
    "rsi": 69.7841,
    "ao": 101.0197
  },
  {
    "time": 1764135300,
    "open": 26118.0996,
    "high": 26126.6992,
    "low": 26111.9492,
    "close": 26117.4004,
    "bb_mid": 26078.5649,
    "bb_upper": 26146.031,
    "bb_lower": 26011.0989,
    "rsi": 69.3267,
    "ao": 102.499
  },
  {
    "time": 1764135600,
    "open": 26117.4492,
    "high": 26118.75,
    "low": 26113.4004,
    "close": 26116.5,
    "bb_mid": 26083.8399,
    "bb_upper": 26145.2925,
    "bb_lower": 26022.3874,
    "rsi": 68.9282,
    "ao": 98.8004
  },
  {
    "time": 1764135900,
    "open": 26116.75,
    "high": 26131.8008,
    "low": 26115.9004,
    "close": 26130.9004,
    "bb_mid": 26090.23,
    "bb_upper": 26142.1753,
    "bb_lower": 26038.2847,
    "rsi": 71.7269,
    "ao": 95.6305
  },
  {
    "time": 1764136200,
    "open": 26129.9492,
    "high": 26135.9492,
    "low": 26127.8496,
    "close": 26130.75,
    "bb_mid": 26095.5375,
    "bb_upper": 26140.4658,
    "bb_lower": 26050.6092,
    "rsi": 71.6544,
    "ao": 95.0435
  },
  {
    "time": 1764136500,
    "open": 26130.4492,
    "high": 26139.25,
    "low": 26127.9004,
    "close": 26131.8008,
    "bb_mid": 26099.6551,
    "bb_upper": 26141.8075,
    "bb_lower": 26057.5026,
    "rsi": 71.8686,
    "ao": 93.0832
  },
  {
    "time": 1764136800,
    "open": 26131.4492,
    "high": 26138.75,
    "low": 26127.3008,
    "close": 26134.9492,
    "bb_mid": 26102.5351,
    "bb_upper": 26146.1173,
    "bb_lower": 26058.9529,
    "rsi": 72.5382,
    "ao": 89.4307
  },
  {
    "time": 1764137100,
    "open": 26135.0,
    "high": 26137.0996,
    "low": 26124.9004,
    "close": 26126.25,
    "bb_mid": 26104.9501,
    "bb_upper": 26148.1473,
    "bb_lower": 26061.7529,
    "rsi": 67.74,
    "ao": 85.4767
  },
  {
    "time": 1764137400,
    "open": 26126.0996,
    "high": 26129.0508,
    "low": 26120.8496,
    "close": 26121.5,
    "bb_mid": 26106.6551,
    "bb_upper": 26149.6269,
    "bb_lower": 26063.6833,
    "rsi": 65.2037,
    "ao": 78.8011
  },
  {
    "time": 1764137700,
    "open": 26121.0508,
    "high": 26132.9004,
    "low": 26116.6992,
    "close": 26131.3496,
    "bb_mid": 26108.5825,
    "bb_upper": 26152.3879,
    "bb_lower": 26064.7772,
    "rsi": 67.8885,
    "ao": 70.5267
  },
  {
    "time": 1764138000,
    "open": 26131.5996,
    "high": 26136.3008,
    "low": 26128.9492,
    "close": 26131.9004,
    "bb_mid": 26110.9525,
    "bb_upper": 26154.3994,
    "bb_lower": 26067.5057,
    "rsi": 68.0371,
    "ao": 62.9514
  },
  {
    "time": 1764138300,
    "open": 26131.4492,
    "high": 26145.3496,
    "low": 26130.3008,
    "close": 26143.4004,
    "bb_mid": 26113.9051,
    "bb_upper": 26157.7638,
    "bb_lower": 26070.0464,
    "rsi": 71.048,
    "ao": 56.2209
  },
  {
    "time": 1764138600,
    "open": 26143.8008,
    "high": 26152.5508,
    "low": 26137.1992,
    "close": 26149.8008,
    "bb_mid": 26117.5401,
    "bb_upper": 26160.5985,
    "bb_lower": 26074.4817,
    "rsi": 72.5952,
    "ao": 50.8033
  },
  {
    "time": 1764138900,
    "open": 26148.5508,
    "high": 26160.1504,
    "low": 26147.75,
    "close": 26158.1992,
    "bb_mid": 26122.0876,
    "bb_upper": 26161.8688,
    "bb_lower": 26082.3064,
    "rsi": 74.5195,
    "ao": 49.3106
  },
  {
    "time": 1764139200,
    "open": 26158.4004,
    "high": 26161.1992,
    "low": 26155.1992,
    "close": 26156.8496,
    "bb_mid": 26125.99,
    "bb_upper": 26163.1162,
    "bb_lower": 26088.8639,
    "rsi": 73.6249,
    "ao": 50.4912
  },
  {
    "time": 1764139500,
    "open": 26156.9492,
    "high": 26159.3496,
    "low": 26150.1992,
    "close": 26150.8008,
    "bb_mid": 26129.1101,
    "bb_upper": 26163.3078,
    "bb_lower": 26094.9123,
    "rsi": 69.5921,
    "ao": 49.6189
  },
  {
    "time": 1764139800,
    "open": 26151.6504,
    "high": 26156.5508,
    "low": 26147.25,
    "close": 26154.75,
    "bb_mid": 26132.2376,
    "bb_upper": 26163.5406,
    "bb_lower": 26100.9346,
    "rsi": 70.7198,
    "ao": 47.8803
  },
  {
    "time": 1764140100,
    "open": 26154.0,
    "high": 26162.0508,
    "low": 26149.1504,
    "close": 26157.5996,
    "bb_mid": 26133.9451,
    "bb_upper": 26166.9112,
    "bb_lower": 26100.9791,
    "rsi": 71.5399,
    "ao": 45.6673
  },
  {
    "time": 1764140400,
    "open": 26157.8008,
    "high": 26162.25,
    "low": 26149.0508,
    "close": 26162.0,
    "bb_mid": 26136.7176,
    "bb_upper": 26169.3076,
    "bb_lower": 26104.1276,
    "rsi": 72.8066,
    "ao": 41.8154
  },
  {
    "time": 1764140700,
    "open": 26161.6992,
    "high": 26168.5508,
    "low": 26160.4004,
    "close": 26167.9004,
    "bb_mid": 26139.6551,
    "bb_upper": 26172.3735,
    "bb_lower": 26106.9367,
    "rsi": 74.4487,
    "ao": 39.3177
  },
  {
    "time": 1764141000,
    "open": 26167.5996,
    "high": 26171.5996,
    "low": 26164.6992,
    "close": 26170.6992,
    "bb_mid": 26142.265,
    "bb_upper": 26176.1839,
    "bb_lower": 26108.3462,
    "rsi": 75.2134,
    "ao": 38.9347
  },
  {
    "time": 1764141300,
    "open": 26170.4492,
    "high": 26172.5,
    "low": 26163.5508,
    "close": 26165.9492,
    "bb_mid": 26144.6925,
    "bb_upper": 26178.0633,
    "bb_lower": 26111.3217,
    "rsi": 71.313,
    "ao": 39.456
  },
  {
    "time": 1764141600,
    "open": 26165.5508,
    "high": 26173.4492,
    "low": 26162.4004,
    "close": 26165.8496,
    "bb_mid": 26147.16,
    "bb_upper": 26179.0172,
    "bb_lower": 26115.3027,
    "rsi": 71.2295,
    "ao": 39.4804
  },
  {
    "time": 1764141900,
    "open": 26165.6504,
    "high": 26173.0996,
    "low": 26160.1504,
    "close": 26172.0508,
    "bb_mid": 26149.2175,
    "bb_upper": 26181.9563,
    "bb_lower": 26116.4786,
    "rsi": 73.3218,
    "ao": 39.4819
  },
  {
    "time": 1764142200,
    "open": 26171.6992,
    "high": 26185.4004,
    "low": 26169.4492,
    "close": 26184.5,
    "bb_mid": 26151.905,
    "bb_upper": 26187.0005,
    "bb_lower": 26116.8095,
    "rsi": 76.9464,
    "ao": 39.3527
  },
  {
    "time": 1764142500,
    "open": 26184.1504,
    "high": 26191.3008,
    "low": 26180.1992,
    "close": 26189.8008,
    "bb_mid": 26154.805,
    "bb_upper": 26192.4019,
    "bb_lower": 26117.208,
    "rsi": 78.2984,
    "ao": 39.9794
  },
  {
    "time": 1764142800,
    "open": 26188.25,
    "high": 26195.25,
    "low": 26188.25,
    "close": 26188.9004,
    "bb_mid": 26157.5025,
    "bb_upper": 26196.8043,
    "bb_lower": 26118.2008,
    "rsi": 77.4673,
    "ao": 41.3456
  },
  {
    "time": 1764143400,
    "open": 26188.5508,
    "high": 26193.9004,
    "low": 26171.8008,
    "close": 26172.6992,
    "bb_mid": 26159.825,
    "bb_upper": 26196.7697,
    "bb_lower": 26122.8803,
    "rsi": 64.2523,
    "ao": 41.0345
  },
  {
    "time": 1764143700,
    "open": 26173.1504,
    "high": 26180.6504,
    "low": 26151.9004,
    "close": 26154.4492,
    "bb_mid": 26161.4725,
    "bb_upper": 26193.8815,
    "bb_lower": 26129.0635,
    "rsi": 53.2356,
    "ao": 38.3483
  },
  {
    "time": 1764144000,
    "open": 26154.3008,
    "high": 26179.4492,
    "low": 26154.25,
    "close": 26171.5508,
    "bb_mid": 26163.4825,
    "bb_upper": 26192.8711,
    "bb_lower": 26134.094,
    "rsi": 60.1337,
    "ao": 33.7112
  },
  {
    "time": 1764144300,
    "open": 26172.0,
    "high": 26179.0508,
    "low": 26170.8008,
    "close": 26177.6504,
    "bb_mid": 26165.77,
    "bb_upper": 26191.7301,
    "bb_lower": 26139.8099,
    "rsi": 62.2713,
    "ao": 29.0184
  },
  {
    "time": 1764144600,
    "open": 26177.3496,
    "high": 26191.25,
    "low": 26172.9004,
    "close": 26173.1504,
    "bb_mid": 26167.2575,
    "bb_upper": 26191.1475,
    "bb_lower": 26143.3675,
    "rsi": 59.7269,
    "ao": 24.9952
  },
  {
    "time": 1764144900,
    "open": 26173.25,
    "high": 26181.9004,
    "low": 26166.8496,
    "close": 26176.6504,
    "bb_mid": 26168.6,
    "bb_upper": 26191.35,
    "bb_lower": 26145.85,
    "rsi": 61.0596,
    "ao": 21.5487
  },
  {
    "time": 1764145200,
    "open": 26176.5,
    "high": 26181.4004,
    "low": 26163.1504,
    "close": 26178.8496,
    "bb_mid": 26169.6325,
    "bb_upper": 26192.2691,
    "bb_lower": 26146.9959,
    "rsi": 61.9125,
    "ao": 20.8987
  },
  {
    "time": 1764145500,
    "open": 26178.8008,
    "high": 26195.4492,
    "low": 26178.0996,
    "close": 26184.5996,
    "bb_mid": 26171.02,
    "bb_upper": 26193.7592,
    "bb_lower": 26148.2809,
    "rsi": 64.125,
    "ao": 22.7785
  },
  {
    "time": 1764145800,
    "open": 26185.0,
    "high": 26211.9492,
    "low": 26182.75,
    "close": 26202.4004,
    "bb_mid": 26173.6,
    "bb_upper": 26198.304,
    "bb_lower": 26148.896,
    "rsi": 69.9454,
    "ao": 24.9684
  },
  {
    "time": 1764146100,
    "open": 26201.9004,
    "high": 26203.8496,
    "low": 26174.8496,
    "close": 26202.1504,
    "bb_mid": 26175.97,
    "bb_upper": 26202.1126,
    "bb_lower": 26149.8274,
    "rsi": 69.7742,
    "ao": 24.2681
  },
  {
    "time": 1764146400,
    "open": 26201.9492,
    "high": 26206.5,
    "low": 26196.75,
    "close": 26197.3496,
    "bb_mid": 26177.9575,
    "bb_upper": 26204.2632,
    "bb_lower": 26151.6519,
    "rsi": 66.4123,
    "ao": 27.4307
  },
  {
    "time": 1764146700,
    "open": 26197.5996,
    "high": 26199.0996,
    "low": 26180.6992,
    "close": 26189.9004,
    "bb_mid": 26179.3525,
    "bb_upper": 26205.0471,
    "bb_lower": 26153.658,
    "rsi": 61.4635,
    "ao": 29.2496
  },
  {
    "time": 1764147000,
    "open": 26189.9004,
    "high": 26198.5508,
    "low": 26188.0996,
    "close": 26196.0,
    "bb_mid": 26180.7575,
    "bb_upper": 26206.8848,
    "bb_lower": 26154.6302,
    "rsi": 63.8395,
    "ao": 28.8024
  },
  {
    "time": 1764147300,
    "open": 26197.25,
    "high": 26199.6504,
    "low": 26167.5996,
    "close": 26168.1992,
    "bb_mid": 26180.6325,
    "bb_upper": 26206.9854,
    "bb_lower": 26154.2797,
    "rsi": 49.0078,
    "ao": 24.5692
  },
  {
    "time": 1764147600,
    "open": 26167.6504,
    "high": 26185.0996,
    "low": 26166.0508,
    "close": 26181.3008,
    "bb_mid": 26181.4001,
    "bb_upper": 26206.8303,
    "bb_lower": 26155.9699,
    "rsi": 54.3862,
    "ao": 20.5033
  },
  {
    "time": 1764147900,
    "open": 26180.9004,
    "high": 26186.0,
    "low": 26177.5508,
    "close": 26181.3496,
    "bb_mid": 26182.1751,
    "bb_upper": 26206.532,
    "bb_lower": 26157.8182,
    "rsi": 54.4055,
    "ao": 14.8621
  },
  {
    "time": 1764148200,
    "open": 26181.3008,
    "high": 26198.5,
    "low": 26179.4004,
    "close": 26188.3496,
    "bb_mid": 26182.99,
    "bb_upper": 26207.009,
    "bb_lower": 26158.9711,
    "rsi": 57.2015,
    "ao": 12.7854
  },
  {
    "time": 1764148500,
    "open": 26187.5508,
    "high": 26194.3496,
    "low": 26175.4004,
    "close": 26175.4004,
    "bb_mid": 26182.5351,
    "bb_upper": 26206.7773,
    "bb_lower": 26158.2929,
    "rsi": 50.9741,
    "ao": 9.5586
  },
  {
    "time": 1764148800,
    "open": 26175.0996,
    "high": 26185.5,
    "low": 26159.0508,
    "close": 26185.3496,
    "bb_mid": 26182.3125,
    "bb_upper": 26206.3547,
    "bb_lower": 26158.2703,
    "rsi": 55.0254,
    "ao": 6.2755
  },
  {
    "time": 1764149100,
    "open": 26184.6992,
    "high": 26196.5996,
    "low": 26182.9004,
    "close": 26188.5,
    "bb_mid": 26182.2925,
    "bb_upper": 26206.3123,
    "bb_lower": 26158.2727,
    "rsi": 56.258,
    "ao": 7.7906
  },
  {
    "time": 1764149400,
    "open": 26191.3496,
    "high": 26206.8008,
    "low": 26191.1992,
    "close": 26197.4004,
    "bb_mid": 26183.5275,
    "bb_upper": 26208.0062,
    "bb_lower": 26159.0489,
    "rsi": 59.6247,
    "ao": 9.9105
  },
  {
    "time": 1764149700,
    "open": 26199.4004,
    "high": 26213.6992,
    "low": 26192.5,
    "close": 26213.5508,
    "bb_mid": 26186.4826,
    "bb_upper": 26210.445,
    "bb_lower": 26162.5203,
    "rsi": 64.9034,
    "ao": 11.4198
  },
  {
    "time": 1764150000,
    "open": 26214.8008,
    "high": 26214.8008,
    "low": 26206.5508,
    "close": 26212.5996,
    "bb_mid": 26188.5351,
    "bb_upper": 26214.0912,
    "bb_lower": 26162.9789,
    "rsi": 64.3697,
    "ao": 14.9358
  },
  {
    "time": 1764150300,
    "open": 26213.5,
    "high": 26213.5,
    "low": 26200.8008,
    "close": 26204.8496,
    "bb_mid": 26189.895,
    "bb_upper": 26215.9032,
    "bb_lower": 26163.8869,
    "rsi": 60.0372,
    "ao": 20.2858
  },
  {
    "time": 1764150600,
    "open": 26205.1504,
    "high": 26211.75,
    "low": 26198.4004,
    "close": 26210.3496,
    "bb_mid": 26191.755,
    "bb_upper": 26218.0402,
    "bb_lower": 26165.4698,
    "rsi": 61.9923,
    "ao": 21.8957
  },
  {
    "time": 1764150900,
    "open": 26210.4492,
    "high": 26210.9004,
    "low": 26196.5996,
    "close": 26202.6992,
    "bb_mid": 26193.0574,
    "bb_upper": 26218.7664,
    "bb_lower": 26167.3484,
    "rsi": 57.7594,
    "ao": 21.431
  },
  {
    "time": 1764215100,
    "open": 26261.25,
    "high": 26261.25,
    "low": 26210.8496,
    "close": 26253.5996,
    "bb_mid": 26196.7949,
    "bb_upper": 26233.2818,
    "bb_lower": 26160.308,
    "rsi": 71.6362,
    "ao": 25.9159
  },
  {
    "time": 1764215400,
    "open": 26251.9492,
    "high": 26289.5996,
    "low": 26248.6504,
    "close": 26274.4004,
    "bb_mid": 26201.285,
    "bb_upper": 26251.1148,
    "bb_lower": 26151.4551,
    "rsi": 75.219,
    "ao": 34.6359
  },
  {
    "time": 1764215700,
    "open": 26274.6992,
    "high": 26289.25,
    "low": 26258.6504,
    "close": 26283.8008,
    "bb_mid": 26205.355,
    "bb_upper": 26267.3747,
    "bb_lower": 26143.3352,
    "rsi": 76.6542,
    "ao": 44.8804
  },
  {
    "time": 1764216000,
    "open": 26285.1504,
    "high": 26286.5996,
    "low": 26270.9492,
    "close": 26279.5996,
    "bb_mid": 26209.2274,
    "bb_upper": 26279.5241,
    "bb_lower": 26138.9308,
    "rsi": 74.5755,
    "ao": 56.36
  },
  {
    "time": 1764216300,
    "open": 26279.9492,
    "high": 26281.5,
    "low": 26251.5508,
    "close": 26251.5508,
    "bb_mid": 26211.9375,
    "bb_upper": 26284.4503,
    "bb_lower": 26139.4247,
    "rsi": 62.4071,
    "ao": 65.9768
  },
  {
    "time": 1764216600,
    "open": 26249.5508,
    "high": 26254.75,
    "low": 26225.1992,
    "close": 26238.0,
    "bb_mid": 26214.3425,
    "bb_upper": 26286.9683,
    "bb_lower": 26141.7166,
    "rsi": 57.5238,
    "ao": 64.9221
  },
  {
    "time": 1764216900,
    "open": 26236.5996,
    "high": 26251.1992,
    "low": 26223.6992,
    "close": 26249.4492,
    "bb_mid": 26217.0149,
    "bb_upper": 26290.7244,
    "bb_lower": 26143.3055,
    "rsi": 60.3471,
    "ao": 57.0664
  },
  {
    "time": 1764217200,
    "open": 26249.75,
    "high": 26267.1992,
    "low": 26242.4004,
    "close": 26259.0996,
    "bb_mid": 26221.56,
    "bb_upper": 26293.7908,
    "bb_lower": 26149.3291,
    "rsi": 62.6034,
    "ao": 51.3819
  },
  {
    "time": 1764217500,
    "open": 26258.6992,
    "high": 26287.75,
    "low": 26258.6992,
    "close": 26284.0,
    "bb_mid": 26226.6949,
    "bb_upper": 26301.4334,
    "bb_lower": 26151.9564,
    "rsi": 67.709,
    "ao": 47.6138
  },
  {
    "time": 1764217800,
    "open": 26283.9004,
    "high": 26295.3496,
    "low": 26277.0508,
    "close": 26288.6504,
    "bb_mid": 26232.06,
    "bb_upper": 26308.479,
    "bb_lower": 26155.641,
    "rsi": 68.572,
    "ao": 48.0216
  },
  {
    "time": 1764218100,
    "open": 26287.75,
    "high": 26304.1504,
    "low": 26287.75,
    "close": 26290.6992,
    "bb_mid": 26237.1774,
    "bb_upper": 26314.9674,
    "bb_lower": 26159.3875,
    "rsi": 68.9655,
    "ao": 55.4197
  },
  {
    "time": 1764218400,
    "open": 26290.9004,
    "high": 26291.3496,
    "low": 26269.5,
    "close": 26283.0,
    "bb_mid": 26242.5574,
    "bb_upper": 26317.1764,
    "bb_lower": 26167.9384,
    "rsi": 65.6394,
    "ao": 60.9119
  },
  {
    "time": 1764218700,
    "open": 26282.6992,
    "high": 26284.8008,
    "low": 26273.9492,
    "close": 26281.1504,
    "bb_mid": 26247.3475,
    "bb_upper": 26318.7334,
    "bb_lower": 26175.9615,
    "rsi": 64.8304,
    "ao": 62.9651
  },
  {
    "time": 1764219000,
    "open": 26281.75,
    "high": 26287.5996,
    "low": 26273.0996,
    "close": 26275.8496,
    "bb_mid": 26251.7149,
    "bb_upper": 26318.4802,
    "bb_lower": 26184.9497,
    "rsi": 62.455,
    "ao": 61.2732
  },
  {
    "time": 1764219300,
    "open": 26276.9492,
    "high": 26279.8496,
    "low": 26265.6504,
    "close": 26279.25,
    "bb_mid": 26255.8074,
    "bb_upper": 26318.4623,
    "bb_lower": 26193.1526,
    "rsi": 63.3819,
    "ao": 55.6281
  },
  {
    "time": 1764219600,
    "open": 26279.4004,
    "high": 26285.4004,
    "low": 26271.9004,
    "close": 26277.25,
    "bb_mid": 26258.9924,
    "bb_upper": 26319.024,
    "bb_lower": 26198.9607,
    "rsi": 62.406,
    "ao": 49.4659
  },
  {
    "time": 1764219900,
    "open": 26276.3496,
    "high": 26286.8008,
    "low": 26273.1504,
    "close": 26285.9004,
    "bb_mid": 26262.6574,
    "bb_upper": 26319.636,
    "bb_lower": 26205.6789,
    "rsi": 64.9217,
    "ao": 46.9458
  },
  {
    "time": 1764220200,
    "open": 26285.8008,
    "high": 26291.9004,
    "low": 26279.4492,
    "close": 26284.5508,
    "bb_mid": 26266.6425,
    "bb_upper": 26317.4074,
    "bb_lower": 26215.8776,
    "rsi": 64.1999,
    "ao": 45.3727
  },
  {
    "time": 1764220500,
    "open": 26285.75,
    "high": 26299.4004,
    "low": 26285.0996,
    "close": 26299.3008,
    "bb_mid": 26271.09,
    "bb_upper": 26316.3801,
    "bb_lower": 26225.8,
    "rsi": 68.3427,
    "ao": 45.0874
  },
  {
    "time": 1764220800,
    "open": 26299.3496,
    "high": 26310.0508,
    "low": 26290.1992,
    "close": 26291.75,
    "bb_mid": 26275.5426,
    "bb_upper": 26308.2975,
    "bb_lower": 26242.7877,
    "rsi": 64.2442,
    "ao": 47.3204
  },
  {
    "time": 1764221100,
    "open": 26291.3008,
    "high": 26292.6504,
    "low": 26283.6504,
    "close": 26291.75,
    "bb_mid": 26277.4501,
    "bb_upper": 26309.2541,
    "bb_lower": 26245.6461,
    "rsi": 64.2442,
    "ao": 46.4314
  },
  {
    "time": 1764221400,
    "open": 26291.0508,
    "high": 26302.1504,
    "low": 26288.8496,
    "close": 26296.0508,
    "bb_mid": 26278.5326,
    "bb_upper": 26311.357,
    "bb_lower": 26245.7082,
    "rsi": 65.6066,
    "ao": 46.2459
  },
  {
    "time": 1764221700,
    "open": 26295.75,
    "high": 26304.5,
    "low": 26294.0,
    "close": 26301.25,
    "bb_mid": 26279.4051,
    "bb_upper": 26313.7131,
    "bb_lower": 26245.097,
    "rsi": 67.2322,
    "ao": 45.3234
  },
  {
    "time": 1764222000,
    "open": 26301.5996,
    "high": 26303.0996,
    "low": 26291.9004,
    "close": 26297.6504,
    "bb_mid": 26280.3076,
    "bb_upper": 26315.5736,
    "bb_lower": 26245.0417,
    "rsi": 64.9436,
    "ao": 42.9698
  },
  {
    "time": 1764222300,
    "open": 26297.6504,
    "high": 26302.3496,
    "low": 26281.5996,
    "close": 26285.25,
    "bb_mid": 26281.9926,
    "bb_upper": 26314.5929,
    "bb_lower": 26249.3923,
    "rsi": 57.6617,
    "ao": 38.3096
  },
  {
    "time": 1764222600,
    "open": 26285.0996,
    "high": 26287.1992,
    "low": 26275.6504,
    "close": 26282.9492,
    "bb_mid": 26284.24,
    "bb_upper": 26309.4246,
    "bb_lower": 26259.0555,
    "rsi": 56.3981,
    "ao": 34.1247
  },
  {
    "time": 1764222900,
    "open": 26283.5996,
    "high": 26285.9004,
    "low": 26278.0996,
    "close": 26279.4492,
    "bb_mid": 26285.74,
    "bb_upper": 26305.0998,
    "bb_lower": 26266.3803,
    "rsi": 54.4437,
    "ao": 28.1975
  },
  {
    "time": 1764223200,
    "open": 26279.25,
    "high": 26280.0,
    "low": 26266.8008,
    "close": 26270.4004,
    "bb_mid": 26286.3051,
    "bb_upper": 26302.8454,
    "bb_lower": 26269.7648,
    "rsi": 49.6527,
    "ao": 20.5673
  },
  {
    "time": 1764223500,
    "open": 26270.5,
    "high": 26274.5508,
    "low": 26262.75,
    "close": 26263.5996,
    "bb_mid": 26285.2851,
    "bb_upper": 26304.6916,
    "bb_lower": 26265.8785,
    "rsi": 46.3514,
    "ao": 12.7489
  },
  {
    "time": 1764223800,
    "open": 26263.4492,
    "high": 26274.4004,
    "low": 26262.75,
    "close": 26269.3008,
    "bb_mid": 26284.3176,
    "bb_upper": 26304.9108,
    "bb_lower": 26263.7244,
    "rsi": 49.3893,
    "ao": 6.1432
  },
  {
    "time": 1764224100,
    "open": 26269.5996,
    "high": 26270.3496,
    "low": 26233.6992,
    "close": 26238.75,
    "bb_mid": 26281.7201,
    "bb_upper": 26310.4296,
    "bb_lower": 26253.0106,
    "rsi": 37.2248,
    "ao": -0.953
  },
  {
    "time": 1764224400,
    "open": 26238.0,
    "high": 26245.6504,
    "low": 26233.4492,
    "close": 26240.6504,
    "bb_mid": 26279.6026,
    "bb_upper": 26313.663,
    "bb_lower": 26245.5422,
    "rsi": 38.2437,
    "ao": -10.396
  },
  {
    "time": 1764224700,
    "open": 26241.1992,
    "high": 26249.8008,
    "low": 26235.6504,
    "close": 26245.4492,
    "bb_mid": 26277.8176,
    "bb_upper": 26315.1239,
    "bb_lower": 26240.5113,
    "rsi": 40.8544,
    "ao": -17.6383
  },
  {
    "time": 1764225000,
    "open": 26244.9492,
    "high": 26262.5508,
    "low": 26242.0996,
    "close": 26243.8008,
    "bb_mid": 26276.2151,
    "bb_upper": 26316.5108,
    "bb_lower": 26235.9195,
    "rsi": 40.2254,
    "ao": -22.332
  },
  {
    "time": 1764225300,
    "open": 26244.75,
    "high": 26245.8008,
    "low": 26228.6504,
    "close": 26238.8496,
    "bb_mid": 26274.1951,
    "bb_upper": 26317.7675,
    "bb_lower": 26230.6227,
    "rsi": 38.317,
    "ao": -28.6365
  },
  {
    "time": 1764225600,
    "open": 26239.3496,
    "high": 26246.8496,
    "low": 26237.8008,
    "close": 26243.9492,
    "bb_mid": 26272.5301,
    "bb_upper": 26318.1098,
    "bb_lower": 26226.9504,
    "rsi": 41.4007,
    "ao": -29.7881
  },
  {
    "time": 1764225900,
    "open": 26244.0,
    "high": 26247.6992,
    "low": 26230.9004,
    "close": 26241.0508,
    "bb_mid": 26270.2876,
    "bb_upper": 26317.4821,
    "bb_lower": 26223.0931,
    "rsi": 40.1714,
    "ao": -28.819
  },
  {
    "time": 1764226200,
    "open": 26241.0508,
    "high": 26244.25,
    "low": 26219.0,
    "close": 26222.1504,
    "bb_mid": 26267.1676,
    "bb_upper": 26318.4641,
    "bb_lower": 26215.871,
    "rsi": 33.2405,
    "ao": -29.6524
  },
  {
    "time": 1764226500,
    "open": 26222.6992,
    "high": 26228.5508,
    "low": 26214.9492,
    "close": 26226.6504,
    "bb_mid": 26263.5351,
    "bb_upper": 26315.5351,
    "bb_lower": 26211.535,
    "rsi": 36.0687,
    "ao": -34.4505
  },
  {
    "time": 1764226800,
    "open": 26227.0508,
    "high": 26230.0,
    "low": 26219.5996,
    "close": 26220.5508,
    "bb_mid": 26259.9751,
    "bb_upper": 26313.5664,
    "bb_lower": 26206.3838,
    "rsi": 33.9681,
    "ao": -36.4893
  },
  {
    "time": 1764227100,
    "open": 26219.8496,
    "high": 26224.3496,
    "low": 26218.8008,
    "close": 26221.9492,
    "bb_mid": 26256.4851,
    "bb_upper": 26310.4536,
    "bb_lower": 26202.5166,
    "rsi": 34.9042,
    "ao": -40.1724
  },
  {
    "time": 1764227400,
    "open": 26222.3008,
    "high": 26248.1504,
    "low": 26222.1992,
    "close": 26247.6504,
    "bb_mid": 26254.065,
    "bb_upper": 26304.8076,
    "bb_lower": 26203.3225,
    "rsi": 49.1664,
    "ao": -40.4202
  },
  {
    "time": 1764227700,
    "open": 26248.1992,
    "high": 26252.6504,
    "low": 26243.1504,
    "close": 26251.3496,
    "bb_mid": 26251.57,
    "bb_upper": 26297.1927,
    "bb_lower": 26205.9474,
    "rsi": 50.836,
    "ao": -36.4203
  },
  {
    "time": 1764228000,
    "open": 26251.5,
    "high": 26256.9492,
    "low": 26235.8008,
    "close": 26241.9492,
    "bb_mid": 26248.785,
    "bb_upper": 26289.0494,
    "bb_lower": 26208.5206,
    "rsi": 46.6434,
    "ao": -30.324
  },
  {
    "time": 1764228300,
    "open": 26240.9004,
    "high": 26244.5996,
    "low": 26236.5996,
    "close": 26237.9004,
    "bb_mid": 26246.4175,
    "bb_upper": 26283.0594,
    "bb_lower": 26209.7756,
    "rsi": 44.9249,
    "ao": -25.5361
  },
  {
    "time": 1764228600,
    "open": 26237.6504,
    "high": 26239.4004,
    "low": 26224.4004,
    "close": 26230.0508,
    "bb_mid": 26243.7726,
    "bb_upper": 26276.7666,
    "bb_lower": 26210.7786,
    "rsi": 41.7158,
    "ao": -22.0438
  },
  {
    "time": 1764228900,
    "open": 26230.0508,
    "high": 26231.6504,
    "low": 26216.1992,
    "close": 26218.25,
    "bb_mid": 26240.7126,
    "bb_upper": 26271.0169,
    "bb_lower": 26210.4083,
    "rsi": 37.3915,
    "ao": -22.663
  },
  {
    "time": 1764229200,
    "open": 26218.6992,
    "high": 26222.5996,
    "low": 26175.8008,
    "close": 26178.3008,
    "bb_mid": 26236.1076,
    "bb_upper": 26274.3642,
    "bb_lower": 26197.8511,
    "rsi": 27.1363,
    "ao": -30.0162
  },
  {
    "time": 1764229500,
    "open": 26177.25,
    "high": 26186.0508,
    "low": 26167.9492,
    "close": 26183.9492,
    "bb_mid": 26232.1251,
    "bb_upper": 26274.6739,
    "bb_lower": 26189.5763,
    "rsi": 30.0572,
    "ao": -41.0751
  },
  {
    "time": 1764229800,
    "open": 26183.9492,
    "high": 26194.4492,
    "low": 26151.4004,
    "close": 26154.6992,
    "bb_mid": 26226.395,
    "bb_upper": 26277.8076,
    "bb_lower": 26174.9824,
    "rsi": 24.5654,
    "ao": -51.5005
  },
  {
    "time": 1764230100,
    "open": 26154.4492,
    "high": 26156.8008,
    "low": 26145.0508,
    "close": 26152.0508,
    "bb_mid": 26222.0601,
    "bb_upper": 26282.8514,
    "bb_lower": 26161.2687,
    "rsi": 24.1354,
    "ao": -63.8998
  },
  {
    "time": 1764230400,
    "open": 26151.8496,
    "high": 26169.5,
    "low": 26145.9004,
    "close": 26168.4004,
    "bb_mid": 26218.4476,
    "bb_upper": 26283.0546,
    "bb_lower": 26153.8406,
    "rsi": 32.0436,
    "ao": -73.3808
  },
  {
    "time": 1764230700,
    "open": 26168.0,
    "high": 26169.4492,
    "low": 26148.5,
    "close": 26151.0508,
    "bb_mid": 26213.7276,
    "bb_upper": 26283.6065,
    "bb_lower": 26143.8488,
    "rsi": 28.6327,
    "ao": -77.506
  },
  {
    "time": 1764231000,
    "open": 26151.1504,
    "high": 26154.3008,
    "low": 26142.1504,
    "close": 26148.4004,
    "bb_mid": 26208.9576,
    "bb_upper": 26283.0879,
    "bb_lower": 26134.8273,
    "rsi": 28.1399,
    "ao": -78.7933
  },
  {
    "time": 1764231300,
    "open": 26148.0508,
    "high": 26164.3008,
    "low": 26143.5996,
    "close": 26162.4492,
    "bb_mid": 26205.1376,
    "bb_upper": 26280.6434,
    "bb_lower": 26129.6318,
    "rsi": 34.5682,
    "ao": -78.6411
  },
  {
    "time": 1764231600,
    "open": 26161.8008,
    "high": 26179.5996,
    "low": 26157.8496,
    "close": 26179.5996,
    "bb_mid": 26201.9201,
    "bb_upper": 26275.9317,
    "bb_lower": 26127.9085,
    "rsi": 41.4536,
    "ao": -71.3527
  },
  {
    "time": 1764231900,
    "open": 26179.0996,
    "high": 26186.0508,
    "low": 26170.0,
    "close": 26185.4492,
    "bb_mid": 26199.14,
    "bb_upper": 26271.1117,
    "bb_lower": 26127.1683,
    "rsi": 43.6323,
    "ao": -63.7222
  },
  {
    "time": 1764232200,
    "open": 26185.3496,
    "high": 26190.0,
    "low": 26168.3008,
    "close": 26177.6504,
    "bb_mid": 26196.915,
    "bb_upper": 26268.6425,
    "bb_lower": 26125.1875,
    "rsi": 41.4193,
    "ao": -56.2062
  },
  {
    "time": 1764232500,
    "open": 26177.1992,
    "high": 26189.8496,
    "low": 26175.9492,
    "close": 26186.5996,
    "bb_mid": 26194.9125,
    "bb_upper": 26265.3696,
    "bb_lower": 26124.4554,
    "rsi": 44.8745,
    "ao": -46.0633
  },
  {
    "time": 1764232800,
    "open": 26185.5,
    "high": 26197.25,
    "low": 26178.9004,
    "close": 26180.9492,
    "bb_mid": 26192.9324,
    "bb_upper": 26262.5769,
    "bb_lower": 26123.2879,
    "rsi": 43.1442,
    "ao": -36.4927
  },
  {
    "time": 1764233100,
    "open": 26180.5,
    "high": 26200.8496,
    "low": 26172.3008,
    "close": 26187.0996,
    "bb_mid": 26191.1899,
    "bb_upper": 26259.5089,
    "bb_lower": 26122.871,
    "rsi": 45.6029,
    "ao": -30.116
  },
  {
    "time": 1764233400,
    "open": 26188.0508,
    "high": 26206.8008,
    "low": 26185.4004,
    "close": 26199.9004,
    "bb_mid": 26188.8024,
    "bb_upper": 26251.9558,
    "bb_lower": 26125.6491,
    "rsi": 50.4097,
    "ao": -24.2274
  },
  {
    "time": 1764233700,
    "open": 26199.1992,
    "high": 26217.5508,
    "low": 26199.1992,
    "close": 26206.0508,
    "bb_mid": 26186.5375,
    "bb_upper": 26243.157,
    "bb_lower": 26129.918,
    "rsi": 52.5779,
    "ao": -16.6097
  },
  {
    "time": 1764234000,
    "open": 26205.5508,
    "high": 26222.4492,
    "low": 26180.5508,
    "close": 26206.9492,
    "bb_mid": 26184.7875,
    "bb_upper": 26236.1117,
    "bb_lower": 26133.4633,
    "rsi": 52.9019,
    "ao": -10.9168
  },
  {
    "time": 1764234300,
    "open": 26205.4004,
    "high": 26218.6504,
    "low": 26196.5,
    "close": 26218.4004,
    "bb_mid": 26183.8125,
    "bb_upper": 26231.5004,
    "bb_lower": 26136.1246,
    "rsi": 56.9395,
    "ao": -5.7095
  },
  {
    "time": 1764234600,
    "open": 26217.0996,
    "high": 26218.9004,
    "low": 26189.8008,
    "close": 26206.1992,
    "bb_mid": 26182.6199,
    "bb_upper": 26226.4783,
    "bb_lower": 26138.7616,
    "rsi": 51.84,
    "ao": -1.1191
  },
  {
    "time": 1764234900,
    "open": 26205.8496,
    "high": 26206.6992,
    "low": 26193.3496,
    "close": 26193.8496,
    "bb_mid": 26181.3999,
    "bb_upper": 26222.3459,
    "bb_lower": 26140.4539,
    "rsi": 47.2294,
    "ao": 0.9216
  },
  {
    "time": 1764235200,
    "open": 26192.9492,
    "high": 26193.8008,
    "low": 26173.3008,
    "close": 26179.1504,
    "bb_mid": 26181.4424,
    "bb_upper": 26222.3766,
    "bb_lower": 26140.5082,
    "rsi": 42.3961,
    "ao": -2.0205
  },
  {
    "time": 1764235500,
    "open": 26177.9004,
    "high": 26201.3008,
    "low": 26173.5996,
    "close": 26186.0508,
    "bb_mid": 26181.5475,
    "bb_upper": 26222.5195,
    "bb_lower": 26140.5754,
    "rsi": 45.2297,
    "ao": -3.3665
  },
  {
    "time": 1764235800,
    "open": 26185.9492,
    "high": 26228.1992,
    "low": 26185.9492,
    "close": 26212.6992,
    "bb_mid": 26184.4475,
    "bb_upper": 26225.6281,
    "bb_lower": 26143.2668,
    "rsi": 54.5318,
    "ao": -2.4299
  },
  {
    "time": 1764236100,
    "open": 26211.5,
    "high": 26221.3008,
    "low": 26202.3008,
    "close": 26213.1992,
    "bb_mid": 26187.5049,
    "bb_upper": 26227.6243,
    "bb_lower": 26147.3855,
    "rsi": 54.6873,
    "ao": -0.131
  },
  {
    "time": 1764236400,
    "open": 26212.8008,
    "high": 26218.8008,
    "low": 26204.3008,
    "close": 26213.1504,
    "bb_mid": 26189.7424,
    "bb_upper": 26230.3639,
    "bb_lower": 26149.1209,
    "rsi": 54.6677,
    "ao": 2.7646
  },
  {
    "time": 1764236700,
    "open": 26212.6504,
    "high": 26226.5508,
    "low": 26207.5996,
    "close": 26223.25,
    "bb_mid": 26193.3523,
    "bb_upper": 26232.2939,
    "bb_lower": 26154.4108,
    "rsi": 58.0291,
    "ao": 9.607
  },
  {
    "time": 1764237000,
    "open": 26221.8008,
    "high": 26234.1992,
    "low": 26212.6504,
    "close": 26220.3008,
    "bb_mid": 26196.9474,
    "bb_upper": 26231.4366,
    "bb_lower": 26162.4581,
    "rsi": 56.7068,
    "ao": 16.8424
  },
  {
    "time": 1764237300,
    "open": 26220.5508,
    "high": 26231.1504,
    "low": 26217.75,
    "close": 26220.8008,
    "bb_mid": 26199.8649,
    "bb_upper": 26231.8478,
    "bb_lower": 26167.8821,
    "rsi": 56.8862,
    "ao": 20.233
  },
  {
    "time": 1764301500,
    "open": 26246.9004,
    "high": 26246.9004,
    "low": 26172.9004,
    "close": 26242.1504,
    "bb_mid": 26202.9925,
    "bb_upper": 26238.6532,
    "bb_lower": 26167.3317,
    "rsi": 63.7858,
    "ao": 20.5963
  },
  {
    "time": 1764301800,
    "open": 26242.9492,
    "high": 26242.9492,
    "low": 26214.3496,
    "close": 26215.4492,
    "bb_mid": 26204.4925,
    "bb_upper": 26239.5651,
    "bb_lower": 26169.4198,
    "rsi": 52.4751,
    "ao": 24.5822
  },
  {
    "time": 1764302100,
    "open": 26215.9004,
    "high": 26241.0,
    "low": 26202.3008,
    "close": 26229.6504,
    "bb_mid": 26207.0925,
    "bb_upper": 26241.49,
    "bb_lower": 26172.695,
    "rsi": 56.8569,
    "ao": 26.2245
  },
  {
    "time": 1764302400,
    "open": 26231.0,
    "high": 26252.5996,
    "low": 26222.0,
    "close": 26252.3496,
    "bb_mid": 26210.38,
    "bb_upper": 26248.8569,
    "bb_lower": 26171.9031,
    "rsi": 62.7663,
    "ao": 29.0965
  },
  {
    "time": 1764302700,
    "open": 26252.4492,
    "high": 26254.4492,
    "low": 26201.6504,
    "close": 26209.5508,
    "bb_mid": 26211.8101,
    "bb_upper": 26247.7218,
    "bb_lower": 26175.8983,
    "rsi": 49.1082,
    "ao": 29.9297
  },
  {
    "time": 1764303000,
    "open": 26211.0,
    "high": 26240.3496,
    "low": 26209.1504,
    "close": 26225.0996,
    "bb_mid": 26213.7101,
    "bb_upper": 26248.1061,
    "bb_lower": 26179.314,
    "rsi": 53.101,
    "ao": 32.8754
  },
  {
    "time": 1764303300,
    "open": 26224.9004,
    "high": 26241.75,
    "low": 26213.75,
    "close": 26238.6992,
    "bb_mid": 26215.65,
    "bb_upper": 26251.1262,
    "bb_lower": 26180.1738,
    "rsi": 56.3283,
    "ao": 31.8558
  },
  {
    "time": 1764303600,
    "open": 26240.0508,
    "high": 26253.5996,
    "low": 26232.5996,
    "close": 26252.4492,
    "bb_mid": 26217.9699,
    "bb_upper": 26256.7203,
    "bb_lower": 26179.2196,
    "rsi": 59.3724,
    "ao": 34.2015
  },
  {
    "time": 1764303900,
    "open": 26254.0508,
    "high": 26254.75,
    "low": 26242.0996,
    "close": 26250.6504,
    "bb_mid": 26220.155,
    "bb_upper": 26261.1521,
    "bb_lower": 26179.1579,
    "rsi": 58.7951,
    "ao": 34.2059
  },
  {
    "time": 1764304200,
    "open": 26252.0996,
    "high": 26261.6992,
    "low": 26247.6504,
    "close": 26257.1504,
    "bb_mid": 26222.0925,
    "bb_upper": 26266.279,
    "bb_lower": 26177.906,
    "rsi": 60.2975,
    "ao": 36.4795
  },
  {
    "time": 1764304500,
    "open": 26257.0508,
    "high": 26267.1992,
    "low": 26256.6992,
    "close": 26262.0996,
    "bb_mid": 26224.8875,
    "bb_upper": 26271.8272,
    "bb_lower": 26177.9478,
    "rsi": 61.4502,
    "ao": 40.8532
  },
  {
    "time": 1764304800,
    "open": 26263.0508,
    "high": 26263.8008,
    "low": 26239.3008,
    "close": 26240.4004,
    "bb_mid": 26227.215,
    "bb_upper": 26272.2526,
    "bb_lower": 26182.1775,
    "rsi": 54.0422,
    "ao": 42.8905
  },
  {
    "time": 1764305100,
    "open": 26240.6504,
    "high": 26245.4492,
    "low": 26227.25,
    "close": 26232.6504,
    "bb_mid": 26229.89,
    "bb_upper": 26268.853,
    "bb_lower": 26190.9271,
    "rsi": 51.6474,
    "ao": 38.9486
  },
  {
    "time": 1764305400,
    "open": 26232.4492,
    "high": 26233.9004,
    "low": 26220.8496,
    "close": 26220.8496,
    "bb_mid": 26231.63,
    "bb_upper": 26265.0659,
    "bb_lower": 26198.194,
    "rsi": 48.1486,
    "ao": 32.5791
  },
  {
    "time": 1764305700,
    "open": 26221.8496,
    "high": 26239.0508,
    "low": 26218.8008,
    "close": 26236.1992,
    "bb_mid": 26232.805,
    "bb_upper": 26265.071,
    "bb_lower": 26200.5389,
    "rsi": 52.6425,
    "ao": 25.6587
  },
  {
    "time": 1764306000,
    "open": 26235.8008,
    "high": 26256.0508,
    "low": 26234.5508,
    "close": 26250.75,
    "bb_mid": 26234.6825,
    "bb_upper": 26266.5122,
    "bb_lower": 26202.8529,
    "rsi": 56.4921,
    "ao": 20.3503
  },
  {
    "time": 1764306300,
    "open": 26250.5,
    "high": 26269.9004,
    "low": 26250.5,
    "close": 26267.6504,
    "bb_mid": 26237.4075,
    "bb_upper": 26270.7702,
    "bb_lower": 26204.0448,
    "rsi": 60.5075,
    "ao": 19.6964
  },
  {
    "time": 1764306600,
    "open": 26267.8496,
    "high": 26274.4492,
    "low": 26264.3496,
    "close": 26274.4492,
    "bb_mid": 26239.9675,
    "bb_upper": 26276.466,
    "bb_lower": 26203.469,
    "rsi": 62.0258,
    "ao": 23.7622
  },
  {
    "time": 1764306900,
    "open": 26273.9492,
    "high": 26280.1992,
    "low": 26269.3008,
    "close": 26273.4492,
    "bb_mid": 26242.6249,
    "bb_upper": 26280.7954,
    "bb_lower": 26204.4544,
    "rsi": 61.6504,
    "ao": 30.6879
  },
  {
    "time": 1764307200,
    "open": 26270.25,
    "high": 26272.75,
    "low": 26260.9492,
    "close": 26271.9004,
    "bb_mid": 26245.1799,
    "bb_upper": 26284.0342,
    "bb_lower": 26206.3256,
    "rsi": 61.0342,
    "ao": 35.9117
  },
  {
    "time": 1764307500,
    "open": 26271.1992,
    "high": 26271.5,
    "low": 26254.3496,
    "close": 26259.4004,
    "bb_mid": 26246.0424,
    "bb_upper": 26285.3764,
    "bb_lower": 26206.7083,
    "rsi": 56.1557,
    "ao": 37.4711
  },
  {
    "time": 1764307800,
    "open": 26259.4004,
    "high": 26268.9004,
    "low": 26252.25,
    "close": 26258.6504,
    "bb_mid": 26248.2024,
    "bb_upper": 26285.1341,
    "bb_lower": 26211.2708,
    "rsi": 55.8672,
    "ao": 36.0108
  },
  {
    "time": 1764308100,
    "open": 26258.0508,
    "high": 26262.4492,
    "low": 26246.0996,
    "close": 26247.9492,
    "bb_mid": 26249.1174,
    "bb_upper": 26285.0058,
    "bb_lower": 26213.229,
    "rsi": 51.7791,
    "ao": 31.4336
  },
  {
    "time": 1764308400,
    "open": 26247.8008,
    "high": 26267.4004,
    "low": 26245.1504,
    "close": 26266.5,
    "bb_mid": 26249.8249,
    "bb_upper": 26286.5302,
    "bb_lower": 26213.1196,
    "rsi": 57.5747,
    "ao": 26.3063
  },
  {
    "time": 1764308700,
    "open": 26266.9004,
    "high": 26273.25,
    "low": 26261.5996,
    "close": 26264.25,
    "bb_mid": 26252.5599,
    "bb_upper": 26284.4679,
    "bb_lower": 26220.6519,
    "rsi": 56.6849,
    "ao": 24.5662
  },
  {
    "time": 1764309000,
    "open": 26263.75,
    "high": 26264.5,
    "low": 26240.9492,
    "close": 26242.9004,
    "bb_mid": 26253.4499,
    "bb_upper": 26283.0417,
    "bb_lower": 26223.8581,
    "rsi": 48.9531,
    "ao": 20.9762
  },
  {
    "time": 1764309300,
    "open": 26242.3496,
    "high": 26247.9492,
    "low": 26236.75,
    "close": 26243.4004,
    "bb_mid": 26253.685,
    "bb_upper": 26282.8551,
    "bb_lower": 26224.5148,
    "rsi": 49.1281,
    "ao": 15.6017
  },
  {
    "time": 1764309600,
    "open": 26243.1504,
    "high": 26250.6992,
    "low": 26240.5508,
    "close": 26245.6992,
    "bb_mid": 26253.3475,
    "bb_upper": 26282.7332,
    "bb_lower": 26223.9617,
    "rsi": 49.9773,
    "ao": 12.1608
  },
  {
    "time": 1764309900,
    "open": 26244.8496,
    "high": 26246.5508,
    "low": 26232.5996,
    "close": 26244.4004,
    "bb_mid": 26253.035,
    "bb_upper": 26282.6733,
    "bb_lower": 26223.3966,
    "rsi": 49.4748,
    "ao": 7.8648
  },
  {
    "time": 1764310200,
    "open": 26244.6504,
    "high": 26250.9004,
    "low": 26234.3496,
    "close": 26247.9492,
    "bb_mid": 26252.5749,
    "bb_upper": 26282.23,
    "bb_lower": 26222.9199,
    "rsi": 50.9266,
    "ao": 1.9983
  },
  {
    "time": 1764310500,
    "open": 26246.9492,
    "high": 26256.9004,
    "low": 26246.0,
    "close": 26256.6992,
    "bb_mid": 26252.3049,
    "bb_upper": 26281.6919,
    "bb_lower": 26222.9179,
    "rsi": 54.4052,
    "ao": 0.5699
  },
  {
    "time": 1764310800,
    "open": 26256.5996,
    "high": 26257.0996,
    "low": 26245.8008,
    "close": 26250.25,
    "bb_mid": 26252.7974,
    "bb_upper": 26281.67,
    "bb_lower": 26223.9247,
    "rsi": 51.5071,
    "ao": 1.379
  },
  {
    "time": 1764311100,
    "open": 26250.0996,
    "high": 26256.25,
    "low": 26238.0508,
    "close": 26247.0996,
    "bb_mid": 26253.5198,
    "bb_upper": 26280.9573,
    "bb_lower": 26226.0824,
    "rsi": 50.1031,
    "ao": 0.9862
  },
  {
    "time": 1764311400,
    "open": 26247.4004,
    "high": 26253.1504,
    "low": 26242.0508,
    "close": 26244.25,
    "bb_mid": 26254.6898,
    "bb_upper": 26277.9371,
    "bb_lower": 26231.4426,
    "rsi": 48.8071,
    "ao": 1.9104
  },
  {
    "time": 1764311700,
    "open": 26243.6992,
    "high": 26249.4004,
    "low": 26232.8496,
    "close": 26235.1992,
    "bb_mid": 26254.6398,
    "bb_upper": 26278.0583,
    "bb_lower": 26231.2214,
    "rsi": 44.8398,
    "ao": 0.6921
  },
  {
    "time": 1764312000,
    "open": 26234.25,
    "high": 26243.4004,
    "low": 26233.3008,
    "close": 26240.75,
    "bb_mid": 26254.1398,
    "bb_upper": 26278.3225,
    "bb_lower": 26229.9572,
    "rsi": 47.6502,
    "ao": -2.2132
  },
  {
    "time": 1764312300,
    "open": 26239.3496,
    "high": 26240.5508,
    "low": 26225.4004,
    "close": 26227.8496,
    "bb_mid": 26252.1498,
    "bb_upper": 26278.1346,
    "bb_lower": 26226.165,
    "rsi": 42.2611,
    "ao": -6.2412
  },
  {
    "time": 1764312600,
    "open": 26227.1992,
    "high": 26234.1992,
    "low": 26220.3008,
    "close": 26222.5996,
    "bb_mid": 26249.5573,
    "bb_upper": 26276.5028,
    "bb_lower": 26222.6119,
    "rsi": 40.2652,
    "ao": -9.9257
  },
  {
    "time": 1764312900,
    "open": 26222.3496,
    "high": 26225.9004,
    "low": 26217.8496,
    "close": 26220.9004,
    "bb_mid": 26246.9299,
    "bb_upper": 26274.3106,
    "bb_lower": 26219.5491,
    "rsi": 39.6131,
    "ao": -14.8892
  },
  {
    "time": 1764313200,
    "open": 26220.0508,
    "high": 26237.9004,
    "low": 26218.0,
    "close": 26237.1992,
    "bb_mid": 26245.1948,
    "bb_upper": 26270.2087,
    "bb_lower": 26220.1809,
    "rsi": 48.2674,
    "ao": -17.6183
  },
  {
    "time": 1764313500,
    "open": 26236.75,
    "high": 26240.1504,
    "low": 26228.9492,
    "close": 26236.1992,
    "bb_mid": 26244.0348,
    "bb_upper": 26268.4188,
    "bb_lower": 26219.6507,
    "rsi": 47.8146,
    "ao": -18.5784
  },
  {
    "time": 1764313800,
    "open": 26235.6504,
    "high": 26235.75,
    "low": 26226.1504,
    "close": 26230.0,
    "bb_mid": 26242.6022,
    "bb_upper": 26266.736,
    "bb_lower": 26218.4685,
    "rsi": 44.9967,
    "ao": -18.6262
  },
  {
    "time": 1764314100,
    "open": 26229.8496,
    "high": 26230.6504,
    "low": 26204.0,
    "close": 26207.8008,
    "bb_mid": 26240.5948,
    "bb_upper": 26269.133,
    "bb_lower": 26212.0567,
    "rsi": 36.664,
    "ao": -19.6965
  },
  {
    "time": 1764314400,
    "open": 26207.75,
    "high": 26217.6992,
    "low": 26205.75,
    "close": 26217.0,
    "bb_mid": 26238.1198,
    "bb_upper": 26265.7705,
    "bb_lower": 26210.4692,
    "rsi": 41.4987,
    "ao": -20.4633
  },
  {
    "time": 1764314700,
    "open": 26217.1504,
    "high": 26228.75,
    "low": 26211.3008,
    "close": 26226.0996,
    "bb_mid": 26236.2123,
    "bb_upper": 26261.4296,
    "bb_lower": 26210.995,
    "rsi": 45.898,
    "ao": -20.8152
  },
  {
    "time": 1764315000,
    "open": 26225.5,
    "high": 26227.4004,
    "low": 26216.0996,
    "close": 26224.4492,
    "bb_mid": 26235.2897,
    "bb_upper": 26260.8249,
    "bb_lower": 26209.7546,
    "rsi": 45.2336,
    "ao": -22.4987
  },
  {
    "time": 1764315300,
    "open": 26223.6504,
    "high": 26225.75,
    "low": 26215.1992,
    "close": 26220.4492,
    "bb_mid": 26234.1422,
    "bb_upper": 26260.2001,
    "bb_lower": 26208.0843,
    "rsi": 43.5868,
    "ao": -24.1269
  },
  {
    "time": 1764315600,
    "open": 26219.8496,
    "high": 26220.75,
    "low": 26212.6504,
    "close": 26217.9004,
    "bb_mid": 26232.7522,
    "bb_upper": 26259.1776,
    "bb_lower": 26206.3269,
    "rsi": 42.5244,
    "ao": -23.9379
  },
  {
    "time": 1764315900,
    "open": 26217.4492,
    "high": 26224.6504,
    "low": 26208.4492,
    "close": 26209.8008,
    "bb_mid": 26231.0223,
    "bb_upper": 26258.7356,
    "bb_lower": 26203.3089,
    "rsi": 39.2503,
    "ao": -22.6089
  },
  {
    "time": 1764316200,
    "open": 26209.75,
    "high": 26227.5,
    "low": 26203.9004,
    "close": 26227.5,
    "bb_mid": 26229.9998,
    "bb_upper": 26256.569,
    "bb_lower": 26203.4306,
    "rsi": 48.5689,
    "ao": -22.6033
  },
  {
    "time": 1764316500,
    "open": 26226.25,
    "high": 26227.3008,
    "low": 26214.8496,
    "close": 26225.0996,
    "bb_mid": 26228.4198,
    "bb_upper": 26251.8802,
    "bb_lower": 26204.9594,
    "rsi": 47.5046,
    "ao": -21.5875
  },
  {
    "time": 1764316800,
    "open": 26225.6504,
    "high": 26234.9004,
    "low": 26223.0996,
    "close": 26229.8008,
    "bb_mid": 26227.3974,
    "bb_upper": 26248.5175,
    "bb_lower": 26206.2772,
    "rsi": 49.8237,
    "ao": -18.6942
  },
  {
    "time": 1764317100,
    "open": 26230.0,
    "high": 26233.1992,
    "low": 26220.1992,
    "close": 26229.5,
    "bb_mid": 26226.5174,
    "bb_upper": 26245.5439,
    "bb_lower": 26207.4908,
    "rsi": 49.6725,
    "ao": -15.2812
  },
  {
    "time": 1764317400,
    "open": 26228.4492,
    "high": 26229.5996,
    "low": 26216.25,
    "close": 26217.6992,
    "bb_mid": 26225.1898,
    "bb_upper": 26242.6472,
    "bb_lower": 26207.7324,
    "rsi": 44.0275,
    "ao": -12.7143
  },
  {
    "time": 1764317700,
    "open": 26217.0,
    "high": 26218.0996,
    "low": 26203.0508,
    "close": 26206.25,
    "bb_mid": 26223.7424,
    "bb_upper": 26242.4605,
    "bb_lower": 26205.0243,
    "rsi": 39.3545,
    "ao": -12.1996
  },
  {
    "time": 1764318000,
    "open": 26206.75,
    "high": 26212.3008,
    "low": 26194.0,
    "close": 26212.25,
    "bb_mid": 26222.3174,
    "bb_upper": 26239.888,
    "bb_lower": 26204.7468,
    "rsi": 42.7819,
    "ao": -14.0956
  },
  {
    "time": 1764318300,
    "open": 26212.5508,
    "high": 26214.6504,
    "low": 26201.75,
    "close": 26208.8008,
    "bb_mid": 26221.3649,
    "bb_upper": 26239.7205,
    "bb_lower": 26203.0094,
    "rsi": 41.3357,
    "ao": -16.9004
  },
  {
    "time": 1764318600,
    "open": 26208.5996,
    "high": 26217.0996,
    "low": 26206.3496,
    "close": 26214.3008,
    "bb_mid": 26220.95,
    "bb_upper": 26239.5614,
    "bb_lower": 26202.3386,
    "rsi": 44.5543,
    "ao": -18.585
  },
  {
    "time": 1764318900,
    "open": 26214.0508,
    "high": 26216.1992,
    "low": 26200.9492,
    "close": 26205.25,
    "bb_mid": 26220.1675,
    "bb_upper": 26240.0597,
    "bb_lower": 26200.2753,
    "rsi": 40.6061,
    "ao": -19.7242
  },
  {
    "time": 1764319200,
    "open": 26204.8008,
    "high": 26208.0,
    "low": 26199.8008,
    "close": 26200.75,
    "bb_mid": 26218.345,
    "bb_upper": 26238.3455,
    "bb_lower": 26198.3445,
    "rsi": 38.7667,
    "ao": -19.6232
  },
  {
    "time": 1764319500,
    "open": 26200.9492,
    "high": 26206.9004,
    "low": 26195.1992,
    "close": 26201.6992,
    "bb_mid": 26216.62,
    "bb_upper": 26236.0806,
    "bb_lower": 26197.1594,
    "rsi": 39.3904,
    "ao": -18.8286
  },
  {
    "time": 1764319800,
    "open": 26201.5996,
    "high": 26201.5996,
    "low": 26194.9004,
    "close": 26201.0996,
    "bb_mid": 26215.175,
    "bb_upper": 26234.744,
    "bb_lower": 26195.606,
    "rsi": 39.1193,
    "ao": -19.4253
  },
  {
    "time": 1764320100,
    "open": 26200.9004,
    "high": 26206.0996,
    "low": 26199.0508,
    "close": 26205.0996,
    "bb_mid": 26215.0399,
    "bb_upper": 26234.8589,
    "bb_lower": 26195.2209,
    "rsi": 41.9873,
    "ao": -20.1669
  },
  {
    "time": 1764320400,
    "open": 26204.9492,
    "high": 26221.5996,
    "low": 26201.3496,
    "close": 26211.0508,
    "bb_mid": 26214.7425,
    "bb_upper": 26234.6161,
    "bb_lower": 26194.8688,
    "rsi": 46.0586,
    "ao": -18.6706
  },
  {
    "time": 1764320700,
    "open": 26209.3008,
    "high": 26222.4492,
    "low": 26207.6504,
    "close": 26216.9492,
    "bb_mid": 26214.285,
    "bb_upper": 26233.467,
    "bb_lower": 26195.1029,
    "rsi": 49.8177,
    "ao": -15.3702
  },
  {
    "time": 1764321000,
    "open": 26216.1504,
    "high": 26219.0508,
    "low": 26201.9492,
    "close": 26205.5508,
    "bb_mid": 26213.34,
    "bb_upper": 26232.2742,
    "bb_lower": 26194.4059,
    "rsi": 43.5078,
    "ao": -12.2757
  },
  {
    "time": 1764321300,
    "open": 26205.3008,
    "high": 26209.5996,
    "low": 26201.9004,
    "close": 26205.75,
    "bb_mid": 26212.6051,
    "bb_upper": 26231.5184,
    "bb_lower": 26193.6917,
    "rsi": 43.6422,
    "ao": -9.558
  },
  {
    "time": 1764321600,
    "open": 26205.9004,
    "high": 26210.1504,
    "low": 26197.9492,
    "close": 26207.0,
    "bb_mid": 26212.0601,
    "bb_upper": 26230.9591,
    "bb_lower": 26193.161,
    "rsi": 44.5336,
    "ao": -7.9822
  },
  {
    "time": 1764321900,
    "open": 26207.5996,
    "high": 26214.4004,
    "low": 26204.5,
    "close": 26209.5508,
    "bb_mid": 26212.0476,
    "bb_upper": 26230.9533,
    "bb_lower": 26193.1419,
    "rsi": 46.3967,
    "ao": -7.4555
  },
  {
    "time": 1764322200,
    "open": 26209.6992,
    "high": 26210.5508,
    "low": 26200.0996,
    "close": 26209.1504,
    "bb_mid": 26211.1301,
    "bb_upper": 26228.6052,
    "bb_lower": 26193.655,
    "rsi": 46.1348,
    "ao": -8.4291
  },
  {
    "time": 1764322500,
    "open": 26209.1504,
    "high": 26213.1504,
    "low": 26201.5508,
    "close": 26206.25,
    "bb_mid": 26210.1876,
    "bb_upper": 26226.4839,
    "bb_lower": 26193.8913,
    "rsi": 44.1884,
    "ao": -8.3053
  },
  {
    "time": 1764322800,
    "open": 26204.9004,
    "high": 26208.1504,
    "low": 26196.1504,
    "close": 26197.5508,
    "bb_mid": 26208.5751,
    "bb_upper": 26222.9715,
    "bb_lower": 26194.1787,
    "rsi": 38.8889,
    "ao": -8.287
  },
  {
    "time": 1764323100,
    "open": 26197.4492,
    "high": 26204.1992,
    "low": 26194.4492,
    "close": 26198.9492,
    "bb_mid": 26207.0476,
    "bb_upper": 26218.2171,
    "bb_lower": 26195.878,
    "rsi": 40.1319,
    "ao": -8.5688
  },
  {
    "time": 1764323400,
    "open": 26199.25,
    "high": 26206.0,
    "low": 26191.9004,
    "close": 26199.75,
    "bb_mid": 26206.1501,
    "bb_upper": 26216.5757,
    "bb_lower": 26195.7245,
    "rsi": 40.8735,
    "ao": -9.8159
  },
  {
    "time": 1764323700,
    "open": 26200.8496,
    "high": 26213.6504,
    "low": 26199.8496,
    "close": 26204.5508,
    "bb_mid": 26206.0651,
    "bb_upper": 26216.5149,
    "bb_lower": 26195.6153,
    "rsi": 45.2522,
    "ao": -8.7133
  },
  {
    "time": 1764560700,
    "open": 26319.9004,
    "high": 26319.9004,
    "low": 26272.25,
    "close": 26285.3008,
    "bb_mid": 26209.7177,
    "bb_upper": 26246.6868,
    "bb_lower": 26172.7485,
    "rsi": 76.6179,
    "ao": 7.1162
  },
  {
    "time": 1764561000,
    "open": 26285.3008,
    "high": 26298.6992,
    "low": 26279.1992,
    "close": 26292.3496,
    "bb_mid": 26213.8951,
    "bb_upper": 26266.1497,
    "bb_lower": 26161.6405,
    "rsi": 77.8129,
    "ao": 22.3694
  },
  {
    "time": 1764561300,
    "open": 26292.5,
    "high": 26299.0508,
    "low": 26279.25,
    "close": 26284.0508,
    "bb_mid": 26217.3826,
    "bb_upper": 26278.3373,
    "bb_lower": 26156.428,
    "rsi": 73.0777,
    "ao": 38.0574
  },
  {
    "time": 1764561600,
    "open": 26284.75,
    "high": 26303.9492,
    "low": 26284.5508,
    "close": 26300.1504,
    "bb_mid": 26222.1276,
    "bb_upper": 26293.0635,
    "bb_lower": 26151.1918,
    "rsi": 76.1144,
    "ao": 54.9343
  },
  {
    "time": 1764561900,
    "open": 26301.0996,
    "high": 26312.5,
    "low": 26293.25,
    "close": 26311.0,
    "bb_mid": 26227.6401,
    "bb_upper": 26308.0797,
    "bb_lower": 26147.2005,
    "rsi": 77.9217,
    "ao": 71.7732
  },
  {
    "time": 1764562200,
    "open": 26311.3496,
    "high": 26314.6992,
    "low": 26281.1992,
    "close": 26287.25,
    "bb_mid": 26231.9177,
    "bb_upper": 26315.583,
    "bb_lower": 26148.2523,
    "rsi": 66.1264,
    "ao": 69.8694
  },
  {
    "time": 1764562500,
    "open": 26286.5508,
    "high": 26297.6504,
    "low": 26277.6992,
    "close": 26295.8008,
    "bb_mid": 26236.6527,
    "bb_upper": 26323.6281,
    "bb_lower": 26149.6774,
    "rsi": 68.0043,
    "ao": 67.527
  },
  {
    "time": 1764562800,
    "open": 26294.3008,
    "high": 26296.0,
    "low": 26270.1992,
    "close": 26273.5508,
    "bb_mid": 26240.0753,
    "bb_upper": 26327.2097,
    "bb_lower": 26152.9409,
    "rsi": 58.8602,
    "ao": 64.3595
  },
  {
    "time": 1764563100,
    "open": 26273.8496,
    "high": 26277.6992,
    "low": 26263.9492,
    "close": 26264.3008,
    "bb_mid": 26242.7378,
    "bb_upper": 26329.3909,
    "bb_lower": 26156.0847,
    "rsi": 55.518,
    "ao": 58.053
  },
  {
    "time": 1764563400,
    "open": 26264.4492,
    "high": 26282.1504,
    "low": 26264.4492,
    "close": 26279.75,
    "bb_mid": 26245.8778,
    "bb_upper": 26333.1455,
    "bb_lower": 26158.6102,
    "rsi": 59.64,
    "ao": 50.602
  },
  {
    "time": 1764563700,
    "open": 26279.75,
    "high": 26290.8496,
    "low": 26277.5996,
    "close": 26285.4004,
    "bb_mid": 26249.8703,
    "bb_upper": 26336.6747,
    "bb_lower": 26163.0659,
    "rsi": 61.0612,
    "ao": 46.2328
  },
  {
    "time": 1764564000,
    "open": 26285.9004,
    "high": 26288.1992,
    "low": 26279.3496,
    "close": 26284.9492,
    "bb_mid": 26253.8303,
    "bb_upper": 26339.3769,
    "bb_lower": 26168.2837,
    "rsi": 60.8769,
    "ao": 43.7741
  },
  {
    "time": 1764564300,
    "open": 26283.6504,
    "high": 26288.6992,
    "low": 26270.5,
    "close": 26279.8008,
    "bb_mid": 26257.4703,
    "bb_upper": 26340.7933,
    "bb_lower": 26174.1473,
    "rsi": 58.6992,
    "ao": 41.4071
  },
  {
    "time": 1764564600,
    "open": 26279.3008,
    "high": 26282.0996,
    "low": 26275.0,
    "close": 26277.3496,
    "bb_mid": 26260.8603,
    "bb_upper": 26341.4463,
    "bb_lower": 26180.2742,
    "rsi": 57.642,
    "ao": 40.953
  },
  {
    "time": 1764564900,
    "open": 26278.75,
    "high": 26282.5508,
    "low": 26268.5996,
    "close": 26281.0996,
    "bb_mid": 26264.4577,
    "bb_upper": 26341.6777,
    "bb_lower": 26187.2377,
    "rsi": 58.8627,
    "ao": 39.2779
  },
  {
    "time": 1764565200,
    "open": 26282.9004,
    "high": 26289.5508,
    "low": 26274.9492,
    "close": 26277.8496,
    "bb_mid": 26268.0377,
    "bb_upper": 26340.3801,
    "bb_lower": 26195.6953,
    "rsi": 57.3209,
    "ao": 36.7051
  },
  {
    "time": 1764565500,
    "open": 26277.5996,
    "high": 26282.5996,
    "low": 26258.3008,
    "close": 26259.4004,
    "bb_mid": 26271.1302,
    "bb_upper": 26335.6506,
    "bb_lower": 26206.6097,
    "rsi": 49.409,
    "ao": 32.313
  },
  {
    "time": 1764565800,
    "open": 26259.75,
    "high": 26268.3008,
    "low": 26258.0996,
    "close": 26258.5996,
    "bb_mid": 26274.1127,
    "bb_upper": 26329.4447,
    "bb_lower": 26218.7807,
    "rsi": 49.0923,
    "ao": 27.4265
  },
  {
    "time": 1764566100,
    "open": 26259.4492,
    "high": 26259.6504,
    "low": 26247.4492,
    "close": 26249.4004,
    "bb_mid": 26276.5952,
    "bb_upper": 26321.3174,
    "bb_lower": 26231.873,
    "rsi": 45.485,
    "ao": 20.9662
  },
  {
    "time": 1764566400,
    "open": 26250.9004,
    "high": 26251.4492,
    "low": 26229.3496,
    "close": 26229.6504,
    "bb_mid": 26277.8502,
    "bb_upper": 26314.7919,
    "bb_lower": 26240.9085,
    "rsi": 38.8797,
    "ao": 12.7737
  },
  {
    "time": 1764566700,
    "open": 26230.5,
    "high": 26241.6504,
    "low": 26229.8496,
    "close": 26238.9492,
    "bb_mid": 26275.5326,
    "bb_upper": 26316.1402,
    "bb_lower": 26234.9251,
    "rsi": 43.0715,
    "ao": 2.3708
  },
  {
    "time": 1764567000,
    "open": 26239.5,
    "high": 26240.5508,
    "low": 26224.5508,
    "close": 26227.8008,
    "bb_mid": 26272.3052,
    "bb_upper": 26317.3077,
    "bb_lower": 26227.3027,
    "rsi": 39.5678,
    "ao": -6.0907
  },
  {
    "time": 1764567300,
    "open": 26228.25,
    "high": 26235.6504,
    "low": 26224.75,
    "close": 26225.8008,
    "bb_mid": 26269.3927,
    "bb_upper": 26318.543,
    "bb_lower": 26220.2423,
    "rsi": 38.9556,
    "ao": -13.2415
  },
  {
    "time": 1764567600,
    "open": 26225.5,
    "high": 26244.1504,
    "low": 26225.4492,
    "close": 26242.4004,
    "bb_mid": 26266.5052,
    "bb_upper": 26314.8257,
    "bb_lower": 26218.1846,
    "rsi": 46.3722,
    "ao": -17.5724
  },
  {
    "time": 1764567900,
    "open": 26242.5996,
    "high": 26247.0996,
    "low": 26236.75,
    "close": 26238.0508,
    "bb_mid": 26262.8577,
    "bb_upper": 26307.9411,
    "bb_lower": 26217.7743,
    "rsi": 44.8351,
    "ao": -18.1916
  },
  {
    "time": 1764568200,
    "open": 26238.5508,
    "high": 26249.1992,
    "low": 26237.4492,
    "close": 26246.1504,
    "bb_mid": 26260.8027,
    "bb_upper": 26304.9416,
    "bb_lower": 26216.6639,
    "rsi": 48.2736,
    "ao": -17.7818
  },
  {
    "time": 1764568500,
    "open": 26246.5,
    "high": 26250.9492,
    "low": 26241.6504,
    "close": 26247.5,
    "bb_mid": 26258.3877,
    "bb_upper": 26299.6559,
    "bb_lower": 26217.1194,
    "rsi": 48.8457,
    "ao": -16.2747
  },
  {
    "time": 1764568800,
    "open": 26248.3496,
    "high": 26261.9004,
    "low": 26245.6504,
    "close": 26259.25,
    "bb_mid": 26257.6727,
    "bb_upper": 26298.3257,
    "bb_lower": 26217.0196,
    "rsi": 53.6524,
    "ao": -12.8633
  },
  {
    "time": 1764569100,
    "open": 26260.1504,
    "high": 26260.6992,
    "low": 26250.0508,
    "close": 26257.5996,
    "bb_mid": 26257.3376,
    "bb_upper": 26297.8709,
    "bb_lower": 26216.8043,
    "rsi": 52.9005,
    "ao": -10.2203
  },
  {
    "time": 1764569400,
    "open": 26258.8496,
    "high": 26261.6504,
    "low": 26208.1504,
    "close": 26211.75,
    "bb_mid": 26253.9376,
    "bb_upper": 26297.8243,
    "bb_lower": 26210.0509,
    "rsi": 37.2729,
    "ao": -12.4355
  },
  {
    "time": 1764569700,
    "open": 26212.3496,
    "high": 26212.3496,
    "low": 26180.4492,
    "close": 26190.6504,
    "bb_mid": 26249.2001,
    "bb_upper": 26298.8625,
    "bb_lower": 26199.5377,
    "rsi": 32.5128,
    "ao": -21.6513
  },
  {
    "time": 1764570000,
    "open": 26191.25,
    "high": 26209.3008,
    "low": 26182.0,
    "close": 26202.6992,
    "bb_mid": 26245.0876,
    "bb_upper": 26295.8943,
    "bb_lower": 26194.2809,
    "rsi": 37.4271,
    "ao": -31.6732
  },
  {
    "time": 1764570300,
    "open": 26203.0996,
    "high": 26217.4004,
    "low": 26199.5,
    "close": 26212.5996,
    "bb_mid": 26241.7275,
    "bb_upper": 26291.7506,
    "bb_lower": 26191.7045,
    "rsi": 41.215,
    "ao": -41.0176
  },
  {
    "time": 1764570600,
    "open": 26213.1504,
    "high": 26216.8496,
    "low": 26196.8496,
    "close": 26197.75,
    "bb_mid": 26237.7476,
    "bb_upper": 26288.4982,
    "bb_lower": 26186.9969,
    "rsi": 37.5439,
    "ao": -50.7256
  },
  {
    "time": 1764570900,
    "open": 26197.5508,
    "high": 26197.5508,
    "low": 26174.75,
    "close": 26174.75,
    "bb_mid": 26232.4301,
    "bb_upper": 26286.2485,
    "bb_lower": 26178.6116,
    "rsi": 32.6874,
    "ao": -57.2425
  },
  {
    "time": 1764571200,
    "open": 26175.8008,
    "high": 26183.6504,
    "low": 26168.9004,
    "close": 26175.6504,
    "bb_mid": 26227.3201,
    "bb_upper": 26282.3737,
    "bb_lower": 26172.2665,
    "rsi": 33.0525,
    "ao": -57.9534
  },
  {
    "time": 1764571500,
    "open": 26175.9004,
    "high": 26177.5,
    "low": 26167.0508,
    "close": 26170.4004,
    "bb_mid": 26222.8701,
    "bb_upper": 26281.2904,
    "bb_lower": 26164.4498,
    "rsi": 31.9639,
    "ao": -59.1909
  },
  {
    "time": 1764571800,
    "open": 26170.5996,
    "high": 26182.3008,
    "low": 26161.1504,
    "close": 26181.9492,
    "bb_mid": 26219.0376,
    "bb_upper": 26277.6453,
    "bb_lower": 26160.4299,
    "rsi": 36.8882,
    "ao": -62.9322
  },
  {
    "time": 1764572100,
    "open": 26181.4492,
    "high": 26188.5508,
    "low": 26176.75,
    "close": 26188.5508,
    "bb_mid": 26215.9951,
    "bb_upper": 26274.283,
    "bb_lower": 26157.7072,
    "rsi": 39.5803,
    "ao": -64.236
  },
  {
    "time": 1764572400,
    "open": 26188.25,
    "high": 26188.25,
    "low": 26157.25,
    "close": 26160.8496,
    "bb_mid": 26212.5551,
    "bb_upper": 26275.393,
    "bb_lower": 26149.7171,
    "rsi": 33.1839,
    "ao": -63.2337
  },
  {
    "time": 1764572700,
    "open": 26162.8496,
    "high": 26167.9004,
    "low": 26154.9492,
    "close": 26159.25,
    "bb_mid": 26208.5701,
    "bb_upper": 26274.3978,
    "bb_lower": 26142.7425,
    "rsi": 32.8537,
    "ao": -62.4906
  },
  {
    "time": 1764573000,
    "open": 26159.75,
    "high": 26169.9004,
    "low": 26149.8496,
    "close": 26164.9492,
    "bb_mid": 26205.4275,
    "bb_upper": 26273.3571,
    "bb_lower": 26137.498,
    "rsi": 35.3229,
    "ao": -61.3464
  },
  {
    "time": 1764573300,
    "open": 26164.5996,
    "high": 26170.6992,
    "low": 26151.8496,
    "close": 26157.3496,
    "bb_mid": 26202.005,
    "bb_upper": 26272.4631,
    "bb_lower": 26131.5468,
    "rsi": 33.5511,
    "ao": -60.2146
  },
  {
    "time": 1764573600,
    "open": 26159.5508,
    "high": 26180.3496,
    "low": 26157.8496,
    "close": 26178.8496,
    "bb_mid": 26198.8274,
    "bb_upper": 26267.3196,
    "bb_lower": 26130.3352,
    "rsi": 42.3596,
    "ao": -59.8601
  },
  {
    "time": 1764573900,
    "open": 26179.3008,
    "high": 26188.5,
    "low": 26168.0996,
    "close": 26184.9492,
    "bb_mid": 26196.1724,
    "bb_upper": 26262.34,
    "bb_lower": 26130.0047,
    "rsi": 44.6032,
    "ao": -55.6347
  },
  {
    "time": 1764574200,
    "open": 26185.9492,
    "high": 26186.4004,
    "low": 26167.6992,
    "close": 26179.9492,
    "bb_mid": 26192.8623,
    "bb_upper": 26255.0039,
    "bb_lower": 26130.7207,
    "rsi": 43.1215,
    "ao": -49.3707
  },
  {
    "time": 1764574500,
    "open": 26180.9004,
    "high": 26184.3008,
    "low": 26172.1504,
    "close": 26175.5996,
    "bb_mid": 26189.2673,
    "bb_upper": 26246.2008,
    "bb_lower": 26132.3338,
    "rsi": 41.82,
    "ao": -42.719
  },
  {
    "time": 1764574800,
    "open": 26175.5,
    "high": 26187.5508,
    "low": 26174.1992,
    "close": 26186.9492,
    "bb_mid": 26185.6522,
    "bb_upper": 26232.0899,
    "bb_lower": 26139.2146,
    "rsi": 46.3687,
    "ao": -35.9261
  },
  {
    "time": 1764575100,
    "open": 26187.0508,
    "high": 26195.6504,
    "low": 26185.1504,
    "close": 26195.1504,
    "bb_mid": 26182.5298,
    "bb_upper": 26214.8505,
    "bb_lower": 26150.2091,
    "rsi": 49.4445,
    "ao": -29.1608
  },
  {
    "time": 1764575400,
    "open": 26195.1992,
    "high": 26195.1992,
    "low": 26173.0,
    "close": 26175.4492,
    "bb_mid": 26180.7147,
    "bb_upper": 26210.0671,
    "bb_lower": 26151.3624,
    "rsi": 43.0563,
    "ao": -25.1141
  },
  {
    "time": 1764575700,
    "open": 26176.1504,
    "high": 26177.5508,
    "low": 26169.0996,
    "close": 26173.5996,
    "bb_mid": 26179.8622,
    "bb_upper": 26208.9891,
    "bb_lower": 26150.7354,
    "rsi": 42.5011,
    "ao": -23.0024
  },
  {
    "time": 1764576000,
    "open": 26174.25,
    "high": 26177.4492,
    "low": 26164.6504,
    "close": 26165.8496,
    "bb_mid": 26178.0197,
    "bb_upper": 26205.6896,
    "bb_lower": 26150.3499,
    "rsi": 40.1642,
    "ao": -21.7272
  },
  {
    "time": 1764576300,
    "open": 26166.6992,
    "high": 26189.8496,
    "low": 26164.6992,
    "close": 26185.6992,
    "bb_mid": 26176.6747,
    "bb_upper": 26199.4492,
    "bb_lower": 26153.9002,
    "rsi": 48.044,
    "ao": -20.2039
  },
  {
    "time": 1764576600,
    "open": 26186.1504,
    "high": 26198.25,
    "low": 26178.8008,
    "close": 26190.9004,
    "bb_mid": 26176.3322,
    "bb_upper": 26197.9489,
    "bb_lower": 26154.7156,
    "rsi": 49.9055,
    "ao": -19.0532
  },
  {
    "time": 1764576900,
    "open": 26192.75,
    "high": 26196.6504,
    "low": 26181.75,
    "close": 26194.75,
    "bb_mid": 26177.3322,
    "bb_upper": 26200.4397,
    "bb_lower": 26154.2247,
    "rsi": 51.2964,
    "ao": -16.664
  },
  {
    "time": 1764577200,
    "open": 26195.25,
    "high": 26196.3008,
    "low": 26185.25,
    "close": 26190.6992,
    "bb_mid": 26178.0847,
    "bb_upper": 26201.9299,
    "bb_lower": 26154.2395,
    "rsi": 49.7317,
    "ao": -11.9453
  },
  {
    "time": 1764577500,
    "open": 26191.3496,
    "high": 26191.5508,
    "low": 26180.0508,
    "close": 26183.0,
    "bb_mid": 26178.7146,
    "bb_upper": 26202.37,
    "bb_lower": 26155.0593,
    "rsi": 46.809,
    "ao": -7.6892
  },
  {
    "time": 1764577800,
    "open": 26182.25,
    "high": 26221.4004,
    "low": 26182.25,
    "close": 26221.1504,
    "bb_mid": 26180.6747,
    "bb_upper": 26211.0114,
    "bb_lower": 26150.338,
    "rsi": 59.5077,
    "ao": -1.8092
  },
  {
    "time": 1764578100,
    "open": 26221.4004,
    "high": 26228.9492,
    "low": 26209.5,
    "close": 26212.3496,
    "bb_mid": 26181.8646,
    "bb_upper": 26215.219,
    "bb_lower": 26148.5103,
    "rsi": 56.1759,
    "ao": 4.9983
  },
  {
    "time": 1764578400,
    "open": 26212.0996,
    "high": 26215.5996,
    "low": 26201.5996,
    "close": 26213.8496,
    "bb_mid": 26184.5146,
    "bb_upper": 26219.2327,
    "bb_lower": 26149.7966,
    "rsi": 56.6217,
    "ao": 9.8995
  },
  {
    "time": 1764578700,
    "open": 26214.5508,
    "high": 26217.5996,
    "low": 26202.8008,
    "close": 26205.9004,
    "bb_mid": 26186.8472,
    "bb_upper": 26220.6753,
    "bb_lower": 26153.019,
    "rsi": 53.5149,
    "ao": 14.8462
  },
  {
    "time": 1764579000,
    "open": 26206.4492,
    "high": 26212.8008,
    "low": 26199.3008,
    "close": 26205.5,
    "bb_mid": 26188.8747,
    "bb_upper": 26222.0308,
    "bb_lower": 26155.7186,
    "rsi": 53.3561,
    "ao": 20.2999
  },
  {
    "time": 1764579300,
    "open": 26206.6992,
    "high": 26212.4492,
    "low": 26201.0,
    "close": 26206.9004,
    "bb_mid": 26191.3522,
    "bb_upper": 26221.8918,
    "bb_lower": 26160.8127,
    "rsi": 53.8717,
    "ao": 22.7106
  },
  {
    "time": 1764579600,
    "open": 26206.5,
    "high": 26207.5,
    "low": 26190.5,
    "close": 26196.9492,
    "bb_mid": 26192.2572,
    "bb_upper": 26222.3055,
    "bb_lower": 26162.2089,
    "rsi": 49.6701,
    "ao": 19.7216
  },
  {
    "time": 1764579900,
    "open": 26197.9492,
    "high": 26200.8008,
    "low": 26182.4004,
    "close": 26182.8496,
    "bb_mid": 26192.1522,
    "bb_upper": 26222.3225,
    "bb_lower": 26161.982,
    "rsi": 44.3877,
    "ao": 16.4629
  },
  {
    "time": 1764580200,
    "open": 26183.4004,
    "high": 26187.6992,
    "low": 26171.5508,
    "close": 26172.5,
    "bb_mid": 26191.7798,
    "bb_upper": 26222.7574,
    "bb_lower": 26160.8021,
    "rsi": 40.9454,
    "ao": 10.8192
  },
  {
    "time": 1764580500,
    "open": 26173.8496,
    "high": 26177.3496,
    "low": 26169.8496,
    "close": 26174.1992,
    "bb_mid": 26191.7098,
    "bb_upper": 26222.8473,
    "bb_lower": 26160.5722,
    "rsi": 41.7442,
    "ao": 5.354
  },
  {
    "time": 1764580800,
    "open": 26175.1992,
    "high": 26175.4492,
    "low": 26139.3496,
    "close": 26140.4492,
    "bb_mid": 26189.3848,
    "bb_upper": 26228.0526,
    "bb_lower": 26150.7169,
    "rsi": 32.3768,
    "ao": -3.0566
  },
  {
    "time": 1764581100,
    "open": 26144.25,
    "high": 26147.6992,
    "low": 26124.8008,
    "close": 26141.9492,
    "bb_mid": 26186.7247,
    "bb_upper": 26230.6806,
    "bb_lower": 26142.7688,
    "rsi": 33.0954,
    "ao": -14.1389
  },
  {
    "time": 1764581400,
    "open": 26147.1992,
    "high": 26180.5508,
    "low": 26137.4004,
    "close": 26180.5508,
    "bb_mid": 26186.9798,
    "bb_upper": 26230.7189,
    "bb_lower": 26143.2407,
    "rsi": 48.3162,
    "ao": -20.1551
  },
  {
    "time": 1764581700,
    "open": 26180.9004,
    "high": 26181.8496,
    "low": 26171.75,
    "close": 26178.3008,
    "bb_mid": 26187.2148,
    "bb_upper": 26230.701,
    "bb_lower": 26143.7287,
    "rsi": 47.636,
    "ao": -20.8532
  },
  {
    "time": 1764582000,
    "open": 26179.0,
    "high": 26189.1504,
    "low": 26175.9492,
    "close": 26179.5,
    "bb_mid": 26187.8974,
    "bb_upper": 26230.3887,
    "bb_lower": 26145.406,
    "rsi": 48.0558,
    "ao": -19.3816
  },
  {
    "time": 1764582300,
    "open": 26179.6504,
    "high": 26179.9492,
    "low": 26170.6992,
    "close": 26179.4004,
    "bb_mid": 26187.5824,
    "bb_upper": 26230.2354,
    "bb_lower": 26144.9294,
    "rsi": 48.0213,
    "ao": -15.5811
  },
  {
    "time": 1764582600,
    "open": 26178.8496,
    "high": 26182.1504,
    "low": 26173.6992,
    "close": 26181.0,
    "bb_mid": 26187.0874,
    "bb_upper": 26229.808,
    "bb_lower": 26144.3668,
    "rsi": 48.6576,
    "ao": -7.3984
  },
  {
    "time": 1764582900,
    "open": 26181.75,
    "high": 26185.0508,
    "low": 26166.9492,
    "close": 26175.9492,
    "bb_mid": 26186.1474,
    "bb_upper": 26228.9853,
    "bb_lower": 26143.3095,
    "rsi": 46.7132,
    "ao": -4.4222
  }
]